Workbook

Sheet Discovery
L2: QLIK SENSE DISCOVERY · WHAT THE APPS CONTAIN
A5: Input: /home/joginder-singh/workspace/qliksense_to_powerbi_premigration/sample_files · generated 2026-10-08 21:41
A7: NAVIGATE | H7: ='Totals'!$B$9 | Q7: ='Totals'!$B$20 | Z7: ='Totals'!$B$21 | AI7: ='Totals'!$B$22 | AR7: SCAN SUMMARY
A8: =HYPERLINK("#'Discovery'!A1","Discovery") | AR8: Input folder | BB8: sample_files
A9: =HYPERLINK("#'Apps'!A1","Apps") | H9: APPS DISCOVERED | Q9: SHEETS | Z9: VISUALIZATIONS ON SHEETS | AI9: VISUALIZATION TYPES USED | AR9: Sub-folders included | BB9: No
A10: =HYPERLINK("#'Sheets'!A1","Sheets") | AR10: Output folder | BB10: output
A11: =HYPERLINK("#'Visualizations'!A1","Visualizations") | AR11: Apps discovered | BB11: ='Totals'!$B$9
A12: =HYPERLINK("#'MasterMeasures'!A1","Master Measures") | H12: ='Totals'!$B$30 | Q12: ='Totals'!$B$35 | Z12: ='Totals'!$B$37 | AI12: ='Totals'!$B$38 | AR12: Apps parsed | BB12: ='Totals'!$B$10
A13: =HYPERLINK("#'MasterDimensions'!A1","Master Dimensions") | AR13: Apps failed | BB13: ='Totals'!$B$11
A14: =HYPERLINK("#'MasterVisualizations'!A1","Master Visuals") | H14: MASTER MEASURES | Q14: MASTER DIMENSIONS | Z14: MASTER VISUALIZATIONS | AI14: VARIABLES | AR14: Total size (MB) | BB14: ='Totals'!$B$12
A15: =HYPERLINK("#'MasterItemUsage'!A1","Master Item Usage") | AR15: Low-complexity apps | BB15: ='Totals'!$B$15
A16: =HYPERLINK("#'Variables'!A1","Variables") | AR16: Medium-complexity apps | BB16: ='Totals'!$B$14
A17: =HYPERLINK("#'Bookmarks'!A1","Bookmarks") | H17: ='Totals'!$B$43 | Q17: ='Totals'!$B$45 | Z17: ='Totals'!$B$47 | AI17: ='Totals'!$B$49 | AR17: High-complexity apps | BB17: ='Totals'!$B$13
A18: =HYPERLINK("#'Stories'!A1","Stories") | AR18: Portfolio effort score | BB18: ='Totals'!$B$16
A19: =HYPERLINK("#'LoadScript'!A1","Load Script") | H19: LOAD SCRIPT TABS | Q19: LOAD STATEMENTS | Z19: DISTINCT EXTERNAL SOURCES | AI19: DATA ROWS STORED | AR19: Bookmarks | BB19: ='Totals'!$B$24
A20: =HYPERLINK("#'DataSources'!A1","Data Sources") | AR20: Stories | BB20: ='Totals'!$B$25
A21: =HYPERLINK("#'DataTables'!A1","Data Tables") | AR21: Legacy QlikView objects | BB21: ='Totals'!$B$51
A22: =HYPERLINK("#'Fields'!A1","Fields") | H22: ='Totals'!$B$13 | Q22: ='Totals'!$B$33 | Z22: ='Totals'!$B$34 | AI22: ='Totals'!$B$56 | AR22: Discovered by | BB22: qvf-app + Kanerika discovery
A23: =HYPERLINK("#'LegacyObjects'!A1","Legacy Objects") | AR23: Generated | BB23: 2026-10-08 21:41
A24: =HYPERLINK("#'ExpressionFunctions'!A1","Functions") | H24: HIGH-COMPLEXITY APPS | Q24: HIGH-COMPLEXITY MEASURES | Z24: UNUSED MASTER MEASURES | AI24: PARSER WARNINGS
A25: =HYPERLINK("#'Media'!A1","Media")
A26: =HYPERLINK("#'StoredObjects'!A1","Stored Objects")
A27: =HYPERLINK("#'Warnings'!A1","Warnings")
A28: =HYPERLINK("#'Information'!A1","Information") | H28: AT A GLANCE
A29: =HYPERLINK("#'Totals'!A1","Totals")

Sheet Apps
C2: Apps · one row per Qlik app
A5: =HYPERLINK("#'Discovery'!A1","« Back to Discovery") | B5: One row per app: file, status, every count, effort score and migration complexity (all formulas).
A6: App | B6: App title | C6: File | D6: Size (MB) | E6: Status | F6: Qlik version | G6: Last reload | H6: Data stored | I6: Sheets | J6: Visualizations | K6: Master measures | L6: Set analysis | M6: Aggr() | N6: High-complexity measures | O6: Master dimensions | P6: Drill-down | Q6: Master visualizations | R6: Variables | S6: Expression variables | T6: Bookmarks | U6: Stories | V6: Script tabs | W6: LOAD statements | X6: Distinct external sources | Y6: Data tables | Z6: Data rows | AA6: Fields | AB6: Legacy objects | AC6: Warnings | AD6: Effort score | AE6: Complexity
A7: Executive Dashboard | B7: Executive Dashboard | C7: Executive Dashboard.qvf | D7: 2.75 | E7: Parsed | F7: 2.1.1 | G7: 2014-06-27 15:51:29 | H7: Yes | I7: =COUNTIF('Sheets'!$A$7:$A$100000,$A7) | J7: =COUNTIF('Visualizations'!$A$7:$A$100000,$A7) | K7: =COUNTIF('MasterMeasures'!$A$7:$A$100000,$A7) | L7: =COUNTIFS('MasterMeasures'!$A$7:$A$100000,$A7,'MasterMeasures'!$G$7:$G$100000,"Yes") | M7: =COUNTIFS('MasterMeasures'!$A$7:$A$100000,$A7,'MasterMeasures'!$H$7:$H$100000,"Yes") | N7: =COUNTIFS('MasterMeasures'!$A$7:$A$100000,$A7,'MasterMeasures'!$K$7:$K$100000,"High") | O7: =COUNTIF('MasterDimensions'!$A$7:$A$100000,$A7) | P7: =COUNTIFS('MasterDimensions'!$A$7:$A$100000,$A7,'MasterDimensions'!$E$7:$E$100000,"Drill-down") | Q7: =COUNTIF('MasterVisualizations'!$A$7:$A$100000,$A7) | R7: =COUNTIF('Variables'!$A$7:$A$100000,$A7) | S7: =COUNTIFS('Variables'!$A$7:$A$100000,$A7,'Variables'!$F$7:$F$100000,"Yes") | T7: =COUNTIF('Bookmarks'!$A$7:$A$100000,$A7) | U7: =COUNTIF('Stories'!$A$7:$A$100000,$A7) | V7: =COUNTIF('LoadScript'!$A$7:$A$100000,$A7) | W7: =SUMIF('LoadScript'!$A$7:$A$100000,$A7,'LoadScript'!$E$7:$E$100000) | X7: =SUMIF('DataSources'!$A$7:$A$100000,$A7,'DataSources'!$F$7:$F$100000) | Y7: =COUNTIF('DataTables'!$A$7:$A$100000,$A7) | Z7: =SUMIF('DataTables'!$A$7:$A$100000,$A7,'DataTables'!$D$7:$D$100000) | AA7: =COUNTIF('Fields'!$A$7:$A$100000,$A7) | AB7: =COUNTIF('LegacyObjects'!$A$7:$A$100000,$A7) | AC7: =COUNTIF('Warnings'!$A$7:$A$100000,$A7) | AD7: =IF($E7="Parsed",I7*'Totals'!$C$77+J7*'Totals'!$C$78+K7*'Totals'!$C$79+L7*'Totals'!$C$80+M7*'Totals'!$C$81+O7*'Totals'!$C$82+P7*'Totals'!$C$83+Q7*'Totals'!$C$84+S7*'Totals'!$C$85+V7*'Totals'!$C$86+W7*'Totals'!$C$87+X7*'Totals'!$C$88+AB7*'Totals'!$C$89+T7*'Totals'!$C$90+U7*'Totals'!$C$91,0) | AE7: =IF($E7<>"Parsed","-",IF(AD7>='Totals'!$C$94,"High",IF(AD7>='Totals'!$C$93,"Medium","Low")))
A8: First Qlikview Report | B8: First Qlikview Report | C8: First Qlikview Report.qvf | D8: 0.21 | E8: Parsed | F8: 12.70.20000 | G8: 2026-09-24 14:00:48 | H8: Yes | I8: =COUNTIF('Sheets'!$A$7:$A$100000,$A8) | J8: =COUNTIF('Visualizations'!$A$7:$A$100000,$A8) | K8: =COUNTIF('MasterMeasures'!$A$7:$A$100000,$A8) | L8: =COUNTIFS('MasterMeasures'!$A$7:$A$100000,$A8,'MasterMeasures'!$G$7:$G$100000,"Yes") | M8: =COUNTIFS('MasterMeasures'!$A$7:$A$100000,$A8,'MasterMeasures'!$H$7:$H$100000,"Yes") | N8: =COUNTIFS('MasterMeasures'!$A$7:$A$100000,$A8,'MasterMeasures'!$K$7:$K$100000,"High") | O8: =COUNTIF('MasterDimensions'!$A$7:$A$100000,$A8) | P8: =COUNTIFS('MasterDimensions'!$A$7:$A$100000,$A8,'MasterDimensions'!$E$7:$E$100000,"Drill-down") | Q8: =COUNTIF('MasterVisualizations'!$A$7:$A$100000,$A8) | R8: =COUNTIF('Variables'!$A$7:$A$100000,$A8) | S8: =COUNTIFS('Variables'!$A$7:$A$100000,$A8,'Variables'!$F$7:$F$100000,"Yes") | T8: =COUNTIF('Bookmarks'!$A$7:$A$100000,$A8) | U8: =COUNTIF('Stories'!$A$7:$A$100000,$A8) | V8: =COUNTIF('LoadScript'!$A$7:$A$100000,$A8) | W8: =SUMIF('LoadScript'!$A$7:$A$100000,$A8,'LoadScript'!$E$7:$E$100000) | X8: =SUMIF('DataSources'!$A$7:$A$100000,$A8,'DataSources'!$F$7:$F$100000) | Y8: =COUNTIF('DataTables'!$A$7:$A$100000,$A8) | Z8: =SUMIF('DataTables'!$A$7:$A$100000,$A8,'DataTables'!$D$7:$D$100000) | AA8: =COUNTIF('Fields'!$A$7:$A$100000,$A8) | AB8: =COUNTIF('LegacyObjects'!$A$7:$A$100000,$A8) | AC8: =COUNTIF('Warnings'!$A$7:$A$100000,$A8) | AD8: =IF($E8="Parsed",I8*'Totals'!$C$77+J8*'Totals'!$C$78+K8*'Totals'!$C$79+L8*'Totals'!$C$80+M8*'Totals'!$C$81+O8*'Totals'!$C$82+P8*'Totals'!$C$83+Q8*'Totals'!$C$84+S8*'Totals'!$C$85+V8*'Totals'!$C$86+W8*'Totals'!$C$87+X8*'Totals'!$C$88+AB8*'Totals'!$C$89+T8*'Totals'!$C$90+U8*'Totals'!$C$91,0) | AE8: =IF($E8<>"Parsed","-",IF(AD8>='Totals'!$C$94,"High",IF(AD8>='Totals'!$C$93,"Medium","Low")))
A9: Helpdesk Management | B9: Helpdesk Management | C9: Helpdesk Management.qvf | D9: 1.88 | E9: Parsed | F9: 2.1.1 | G9: 1753-01-01 00:00:00 | H9: Yes | I9: =COUNTIF('Sheets'!$A$7:$A$100000,$A9) | J9: =COUNTIF('Visualizations'!$A$7:$A$100000,$A9) | K9: =COUNTIF('MasterMeasures'!$A$7:$A$100000,$A9) | L9: =COUNTIFS('MasterMeasures'!$A$7:$A$100000,$A9,'MasterMeasures'!$G$7:$G$100000,"Yes") | M9: =COUNTIFS('MasterMeasures'!$A$7:$A$100000,$A9,'MasterMeasures'!$H$7:$H$100000,"Yes") | N9: =COUNTIFS('MasterMeasures'!$A$7:$A$100000,$A9,'MasterMeasures'!$K$7:$K$100000,"High") | O9: =COUNTIF('MasterDimensions'!$A$7:$A$100000,$A9) | P9: =COUNTIFS('MasterDimensions'!$A$7:$A$100000,$A9,'MasterDimensions'!$E$7:$E$100000,"Drill-down") | Q9: =COUNTIF('MasterVisualizations'!$A$7:$A$100000,$A9) | R9: =COUNTIF('Variables'!$A$7:$A$100000,$A9) | S9: =COUNTIFS('Variables'!$A$7:$A$100000,$A9,'Variables'!$F$7:$F$100000,"Yes") | T9: =COUNTIF('Bookmarks'!$A$7:$A$100000,$A9) | U9: =COUNTIF('Stories'!$A$7:$A$100000,$A9) | V9: =COUNTIF('LoadScript'!$A$7:$A$100000,$A9) | W9: =SUMIF('LoadScript'!$A$7:$A$100000,$A9,'LoadScript'!$E$7:$E$100000) | X9: =SUMIF('DataSources'!$A$7:$A$100000,$A9,'DataSources'!$F$7:$F$100000) | Y9: =COUNTIF('DataTables'!$A$7:$A$100000,$A9) | Z9: =SUMIF('DataTables'!$A$7:$A$100000,$A9,'DataTables'!$D$7:$D$100000) | AA9: =COUNTIF('Fields'!$A$7:$A$100000,$A9) | AB9: =COUNTIF('LegacyObjects'!$A$7:$A$100000,$A9) | AC9: =COUNTIF('Warnings'!$A$7:$A$100000,$A9) | AD9: =IF($E9="Parsed",I9*'Totals'!$C$77+J9*'Totals'!$C$78+K9*'Totals'!$C$79+L9*'Totals'!$C$80+M9*'Totals'!$C$81+O9*'Totals'!$C$82+P9*'Totals'!$C$83+Q9*'Totals'!$C$84+S9*'Totals'!$C$85+V9*'Totals'!$C$86+W9*'Totals'!$C$87+X9*'Totals'!$C$88+AB9*'Totals'!$C$89+T9*'Totals'!$C$90+U9*'Totals'!$C$91,0) | AE9: =IF($E9<>"Parsed","-",IF(AD9>='Totals'!$C$94,"High",IF(AD9>='Totals'!$C$93,"Medium","Low")))
A10: Sales Analysis | B10: Sales Analysis | C10: Sales Analysis.qvf | D10: 0.28 | E10: Parsed | F10: 2.1.1 | G10: 2016-01-24 21:04:00 | H10: Yes | I10: =COUNTIF('Sheets'!$A$7:$A$100000,$A10) | J10: =COUNTIF('Visualizations'!$A$7:$A$100000,$A10) | K10: =COUNTIF('MasterMeasures'!$A$7:$A$100000,$A10) | L10: =COUNTIFS('MasterMeasures'!$A$7:$A$100000,$A10,'MasterMeasures'!$G$7:$G$100000,"Yes") | M10: =COUNTIFS('MasterMeasures'!$A$7:$A$100000,$A10,'MasterMeasures'!$H$7:$H$100000,"Yes") | N10: =COUNTIFS('MasterMeasures'!$A$7:$A$100000,$A10,'MasterMeasures'!$K$7:$K$100000,"High") | O10: =COUNTIF('MasterDimensions'!$A$7:$A$100000,$A10) | P10: =COUNTIFS('MasterDimensions'!$A$7:$A$100000,$A10,'MasterDimensions'!$E$7:$E$100000,"Drill-down") | Q10: =COUNTIF('MasterVisualizations'!$A$7:$A$100000,$A10) | R10: =COUNTIF('Variables'!$A$7:$A$100000,$A10) | S10: =COUNTIFS('Variables'!$A$7:$A$100000,$A10,'Variables'!$F$7:$F$100000,"Yes") | T10: =COUNTIF('Bookmarks'!$A$7:$A$100000,$A10) | U10: =COUNTIF('Stories'!$A$7:$A$100000,$A10) | V10: =COUNTIF('LoadScript'!$A$7:$A$100000,$A10) | W10: =SUMIF('LoadScript'!$A$7:$A$100000,$A10,'LoadScript'!$E$7:$E$100000) | X10: =SUMIF('DataSources'!$A$7:$A$100000,$A10,'DataSources'!$F$7:$F$100000) | Y10: =COUNTIF('DataTables'!$A$7:$A$100000,$A10) | Z10: =SUMIF('DataTables'!$A$7:$A$100000,$A10,'DataTables'!$D$7:$D$100000) | AA10: =COUNTIF('Fields'!$A$7:$A$100000,$A10) | AB10: =COUNTIF('LegacyObjects'!$A$7:$A$100000,$A10) | AC10: =COUNTIF('Warnings'!$A$7:$A$100000,$A10) | AD10: =IF($E10="Parsed",I10*'Totals'!$C$77+J10*'Totals'!$C$78+K10*'Totals'!$C$79+L10*'Totals'!$C$80+M10*'Totals'!$C$81+O10*'Totals'!$C$82+P10*'Totals'!$C$83+Q10*'Totals'!$C$84+S10*'Totals'!$C$85+V10*'Totals'!$C$86+W10*'Totals'!$C$87+X10*'Totals'!$C$88+AB10*'Totals'!$C$89+T10*'Totals'!$C$90+U10*'Totals'!$C$91,0) | AE10: =IF($E10<>"Parsed","-",IF(AD10>='Totals'!$C$94,"High",IF(AD10>='Totals'!$C$93,"Medium","Low")))
A11: TryConfigColorAndAgrField | B11: TryConfigColorAndAgrField | C11: TryConfigColorAndAgrField.qvf | D11: 0.17 | E11: Parsed | F11: 2.1.1 | G11: 2016-03-06 16:53:12 | H11: Yes | I11: =COUNTIF('Sheets'!$A$7:$A$100000,$A11) | J11: =COUNTIF('Visualizations'!$A$7:$A$100000,$A11) | K11: =COUNTIF('MasterMeasures'!$A$7:$A$100000,$A11) | L11: =COUNTIFS('MasterMeasures'!$A$7:$A$100000,$A11,'MasterMeasures'!$G$7:$G$100000,"Yes") | M11: =COUNTIFS('MasterMeasures'!$A$7:$A$100000,$A11,'MasterMeasures'!$H$7:$H$100000,"Yes") | N11: =COUNTIFS('MasterMeasures'!$A$7:$A$100000,$A11,'MasterMeasures'!$K$7:$K$100000,"High") | O11: =COUNTIF('MasterDimensions'!$A$7:$A$100000,$A11) | P11: =COUNTIFS('MasterDimensions'!$A$7:$A$100000,$A11,'MasterDimensions'!$E$7:$E$100000,"Drill-down") | Q11: =COUNTIF('MasterVisualizations'!$A$7:$A$100000,$A11) | R11: =COUNTIF('Variables'!$A$7:$A$100000,$A11) | S11: =COUNTIFS('Variables'!$A$7:$A$100000,$A11,'Variables'!$F$7:$F$100000,"Yes") | T11: =COUNTIF('Bookmarks'!$A$7:$A$100000,$A11) | U11: =COUNTIF('Stories'!$A$7:$A$100000,$A11) | V11: =COUNTIF('LoadScript'!$A$7:$A$100000,$A11) | W11: =SUMIF('LoadScript'!$A$7:$A$100000,$A11,'LoadScript'!$E$7:$E$100000) | X11: =SUMIF('DataSources'!$A$7:$A$100000,$A11,'DataSources'!$F$7:$F$100000) | Y11: =COUNTIF('DataTables'!$A$7:$A$100000,$A11) | Z11: =SUMIF('DataTables'!$A$7:$A$100000,$A11,'DataTables'!$D$7:$D$100000) | AA11: =COUNTIF('Fields'!$A$7:$A$100000,$A11) | AB11: =COUNTIF('LegacyObjects'!$A$7:$A$100000,$A11) | AC11: =COUNTIF('Warnings'!$A$7:$A$100000,$A11) | AD11: =IF($E11="Parsed",I11*'Totals'!$C$77+J11*'Totals'!$C$78+K11*'Totals'!$C$79+L11*'Totals'!$C$80+M11*'Totals'!$C$81+O11*'Totals'!$C$82+P11*'Totals'!$C$83+Q11*'Totals'!$C$84+S11*'Totals'!$C$85+V11*'Totals'!$C$86+W11*'Totals'!$C$87+X11*'Totals'!$C$88+AB11*'Totals'!$C$89+T11*'Totals'!$C$90+U11*'Totals'!$C$91,0) | AE11: =IF($E11<>"Parsed","-",IF(AD11>='Totals'!$C$94,"High",IF(AD11>='Totals'!$C$93,"Medium","Low")))
A12: TryExtensions | B12: TryExtensions | C12: TryExtensions.qvf | D12: 0.2 | E12: Parsed | F12: 2.1.1 | G12: 2015-11-29 22:54:00 | H12: Yes | I12: =COUNTIF('Sheets'!$A$7:$A$100000,$A12) | J12: =COUNTIF('Visualizations'!$A$7:$A$100000,$A12) | K12: =COUNTIF('MasterMeasures'!$A$7:$A$100000,$A12) | L12: =COUNTIFS('MasterMeasures'!$A$7:$A$100000,$A12,'MasterMeasures'!$G$7:$G$100000,"Yes") | M12: =COUNTIFS('MasterMeasures'!$A$7:$A$100000,$A12,'MasterMeasures'!$H$7:$H$100000,"Yes") | N12: =COUNTIFS('MasterMeasures'!$A$7:$A$100000,$A12,'MasterMeasures'!$K$7:$K$100000,"High") | O12: =COUNTIF('MasterDimensions'!$A$7:$A$100000,$A12) | P12: =COUNTIFS('MasterDimensions'!$A$7:$A$100000,$A12,'MasterDimensions'!$E$7:$E$100000,"Drill-down") | Q12: =COUNTIF('MasterVisualizations'!$A$7:$A$100000,$A12) | R12: =COUNTIF('Variables'!$A$7:$A$100000,$A12) | S12: =COUNTIFS('Variables'!$A$7:$A$100000,$A12,'Variables'!$F$7:$F$100000,"Yes") | T12: =COUNTIF('Bookmarks'!$A$7:$A$100000,$A12) | U12: =COUNTIF('Stories'!$A$7:$A$100000,$A12) | V12: =COUNTIF('LoadScript'!$A$7:$A$100000,$A12) | W12: =SUMIF('LoadScript'!$A$7:$A$100000,$A12,'LoadScript'!$E$7:$E$100000) | X12: =SUMIF('DataSources'!$A$7:$A$100000,$A12,'DataSources'!$F$7:$F$100000) | Y12: =COUNTIF('DataTables'!$A$7:$A$100000,$A12) | Z12: =SUMIF('DataTables'!$A$7:$A$100000,$A12,'DataTables'!$D$7:$D$100000) | AA12: =COUNTIF('Fields'!$A$7:$A$100000,$A12) | AB12: =COUNTIF('LegacyObjects'!$A$7:$A$100000,$A12) | AC12: =COUNTIF('Warnings'!$A$7:$A$100000,$A12) | AD12: =IF($E12="Parsed",I12*'Totals'!$C$77+J12*'Totals'!$C$78+K12*'Totals'!$C$79+L12*'Totals'!$C$80+M12*'Totals'!$C$81+O12*'Totals'!$C$82+P12*'Totals'!$C$83+Q12*'Totals'!$C$84+S12*'Totals'!$C$85+V12*'Totals'!$C$86+W12*'Totals'!$C$87+X12*'Totals'!$C$88+AB12*'Totals'!$C$89+T12*'Totals'!$C$90+U12*'Totals'!$C$91,0) | AE12: =IF($E12<>"Parsed","-",IF(AD12>='Totals'!$C$94,"High",IF(AD12>='Totals'!$C$93,"Medium","Low")))
A13: Tutorial creazione nuova app | B13: Tutorial creazione nuova app | C13: Tutorial creazione nuova app.qvf | D13: 2.43 | E13: Parsed | F13: 2.1.1 | G13: 2016-01-31 18:25:09 | H13: Yes | I13: =COUNTIF('Sheets'!$A$7:$A$100000,$A13) | J13: =COUNTIF('Visualizations'!$A$7:$A$100000,$A13) | K13: =COUNTIF('MasterMeasures'!$A$7:$A$100000,$A13) | L13: =COUNTIFS('MasterMeasures'!$A$7:$A$100000,$A13,'MasterMeasures'!$G$7:$G$100000,"Yes") | M13: =COUNTIFS('MasterMeasures'!$A$7:$A$100000,$A13,'MasterMeasures'!$H$7:$H$100000,"Yes") | N13: =COUNTIFS('MasterMeasures'!$A$7:$A$100000,$A13,'MasterMeasures'!$K$7:$K$100000,"High") | O13: =COUNTIF('MasterDimensions'!$A$7:$A$100000,$A13) | P13: =COUNTIFS('MasterDimensions'!$A$7:$A$100000,$A13,'MasterDimensions'!$E$7:$E$100000,"Drill-down") | Q13: =COUNTIF('MasterVisualizations'!$A$7:$A$100000,$A13) | R13: =COUNTIF('Variables'!$A$7:$A$100000,$A13) | S13: =COUNTIFS('Variables'!$A$7:$A$100000,$A13,'Variables'!$F$7:$F$100000,"Yes") | T13: =COUNTIF('Bookmarks'!$A$7:$A$100000,$A13) | U13: =COUNTIF('Stories'!$A$7:$A$100000,$A13) | V13: =COUNTIF('LoadScript'!$A$7:$A$100000,$A13) | W13: =SUMIF('LoadScript'!$A$7:$A$100000,$A13,'LoadScript'!$E$7:$E$100000) | X13: =SUMIF('DataSources'!$A$7:$A$100000,$A13,'DataSources'!$F$7:$F$100000) | Y13: =COUNTIF('DataTables'!$A$7:$A$100000,$A13) | Z13: =SUMIF('DataTables'!$A$7:$A$100000,$A13,'DataTables'!$D$7:$D$100000) | AA13: =COUNTIF('Fields'!$A$7:$A$100000,$A13) | AB13: =COUNTIF('LegacyObjects'!$A$7:$A$100000,$A13) | AC13: =COUNTIF('Warnings'!$A$7:$A$100000,$A13) | AD13: =IF($E13="Parsed",I13*'Totals'!$C$77+J13*'Totals'!$C$78+K13*'Totals'!$C$79+L13*'Totals'!$C$80+M13*'Totals'!$C$81+O13*'Totals'!$C$82+P13*'Totals'!$C$83+Q13*'Totals'!$C$84+S13*'Totals'!$C$85+V13*'Totals'!$C$86+W13*'Totals'!$C$87+X13*'Totals'!$C$88+AB13*'Totals'!$C$89+T13*'Totals'!$C$90+U13*'Totals'!$C$91,0) | AE13: =IF($E13<>"Parsed","-",IF(AD13>='Totals'!$C$94,"High",IF(AD13>='Totals'!$C$93,"Medium","Low")))
A14: Tutorial creazione script | B14: Tutorial creazione script | C14: Tutorial creazione script.qvf | D14: 0.2 | E14: Parsed | F14: 2.1.1 | G14: 2016-01-31 23:06:30 | H14: Yes | I14: =COUNTIF('Sheets'!$A$7:$A$100000,$A14) | J14: =COUNTIF('Visualizations'!$A$7:$A$100000,$A14) | K14: =COUNTIF('MasterMeasures'!$A$7:$A$100000,$A14) | L14: =COUNTIFS('MasterMeasures'!$A$7:$A$100000,$A14,'MasterMeasures'!$G$7:$G$100000,"Yes") | M14: =COUNTIFS('MasterMeasures'!$A$7:$A$100000,$A14,'MasterMeasures'!$H$7:$H$100000,"Yes") | N14: =COUNTIFS('MasterMeasures'!$A$7:$A$100000,$A14,'MasterMeasures'!$K$7:$K$100000,"High") | O14: =COUNTIF('MasterDimensions'!$A$7:$A$100000,$A14) | P14: =COUNTIFS('MasterDimensions'!$A$7:$A$100000,$A14,'MasterDimensions'!$E$7:$E$100000,"Drill-down") | Q14: =COUNTIF('MasterVisualizations'!$A$7:$A$100000,$A14) | R14: =COUNTIF('Variables'!$A$7:$A$100000,$A14) | S14: =COUNTIFS('Variables'!$A$7:$A$100000,$A14,'Variables'!$F$7:$F$100000,"Yes") | T14: =COUNTIF('Bookmarks'!$A$7:$A$100000,$A14) | U14: =COUNTIF('Stories'!$A$7:$A$100000,$A14) | V14: =COUNTIF('LoadScript'!$A$7:$A$100000,$A14) | W14: =SUMIF('LoadScript'!$A$7:$A$100000,$A14,'LoadScript'!$E$7:$E$100000) | X14: =SUMIF('DataSources'!$A$7:$A$100000,$A14,'DataSources'!$F$7:$F$100000) | Y14: =COUNTIF('DataTables'!$A$7:$A$100000,$A14) | Z14: =SUMIF('DataTables'!$A$7:$A$100000,$A14,'DataTables'!$D$7:$D$100000) | AA14: =COUNTIF('Fields'!$A$7:$A$100000,$A14) | AB14: =COUNTIF('LegacyObjects'!$A$7:$A$100000,$A14) | AC14: =COUNTIF('Warnings'!$A$7:$A$100000,$A14) | AD14: =IF($E14="Parsed",I14*'Totals'!$C$77+J14*'Totals'!$C$78+K14*'Totals'!$C$79+L14*'Totals'!$C$80+M14*'Totals'!$C$81+O14*'Totals'!$C$82+P14*'Totals'!$C$83+Q14*'Totals'!$C$84+S14*'Totals'!$C$85+V14*'Totals'!$C$86+W14*'Totals'!$C$87+X14*'Totals'!$C$88+AB14*'Totals'!$C$89+T14*'Totals'!$C$90+U14*'Totals'!$C$91,0) | AE14: =IF($E14<>"Parsed","-",IF(AD14>='Totals'!$C$94,"High",IF(AD14>='Totals'!$C$93,"Medium","Low")))

Sheet Sheets
D2: Sheets · every sheet in every app
A5: =HYPERLINK("#'Discovery'!A1","« Back to Discovery") | B5: One row per sheet in every app: title, description, visualizations on it, master-item reuse.
A6: App | B6: # | C6: Sheet ID | D6: Title | E6: Description | F6: Visualizations | G6: Linked to master items | H6: Grid (cols x rows)
A7: Executive Dashboard | B7: 1 | C7: PfKsJK | D7: KPI Dashboard | E7: The KPI Dashboard provides a high-level overview of the company in three areas: expenses, revenue and account receivables. | F7: =COUNTIFS('Visualizations'!$A$7:$A$100000,A7,'Visualizations'!$B$7:$B$100000,C7) | G7: =COUNTIFS('Visualizations'!$A$7:$A$100000,A7,'Visualizations'!$B$7:$B$100000,C7,'Visualizations'!$H$7:$H$100000,"?*") | H7: 24 x 12
A8: Executive Dashboard | B8: 2 | C8: FaQeFa | D8: Sales Analysis | E8: The Sales Analysis sheet allows the user to monitor the company's revenue to ensure it is on target for the year. | F8: =COUNTIFS('Visualizations'!$A$7:$A$100000,A8,'Visualizations'!$B$7:$B$100000,C8) | G8: =COUNTIFS('Visualizations'!$A$7:$A$100000,A8,'Visualizations'!$B$7:$B$100000,C8,'Visualizations'!$H$7:$H$100000,"?*") | H8: 24 x 12
A9: Executive Dashboard | B9: 3 | C9: JsCeVm | D9: Account Receivable Analysis | E9: The Account Receivables Analysis sheet provides sales information and a look at the amount due and days sales outstanding for customers. | F9: =COUNTIFS('Visualizations'!$A$7:$A$100000,A9,'Visualizations'!$B$7:$B$100000,C9) | G9: =COUNTIFS('Visualizations'!$A$7:$A$100000,A9,'Visualizations'!$B$7:$B$100000,C9,'Visualizations'!$H$7:$H$100000,"?*") | H9: 24 x 12
A10: Helpdesk Management | B10: 1 | C10: 1ff88551-9c4d-41e0-b790-37f4c11d3df8 | D10: Dashboard | E10: Quickly analyze the pulse of the Helpdesk organization. See the case priority breakdown, cases by department, cases by type, etc. | F10: =COUNTIFS('Visualizations'!$A$7:$A$100000,A10,'Visualizations'!$B$7:$B$100000,C10) | G10: =COUNTIFS('Visualizations'!$A$7:$A$100000,A10,'Visualizations'!$B$7:$B$100000,C10,'Visualizations'!$H$7:$H$100000,"?*") | H10: 24 x 12
A11: Helpdesk Management | B11: 2 | C11: kHgmg | D11: Performance | E11: See employee resource breakdown for each case. Who has the most open cases? Which employee's average case duration is the longest? | F11: =COUNTIFS('Visualizations'!$A$7:$A$100000,A11,'Visualizations'!$B$7:$B$100000,C11) | G11: =COUNTIFS('Visualizations'!$A$7:$A$100000,A11,'Visualizations'!$B$7:$B$100000,C11,'Visualizations'!$H$7:$H$100000,"?*") | H11: 24 x 12
A12: Helpdesk Management | B12: 3 | C12: VkcYvCR | D12: Case Details | E12: See an overview of each case. Filter by department, type, open cases, closed cases, etc | F12: =COUNTIFS('Visualizations'!$A$7:$A$100000,A12,'Visualizations'!$B$7:$B$100000,C12) | G12: =COUNTIFS('Visualizations'!$A$7:$A$100000,A12,'Visualizations'!$B$7:$B$100000,C12,'Visualizations'!$H$7:$H$100000,"?*") | H12: 24 x 12
A13: Sales Analysis | B13: 1 | C13: RpwpQEp | D13: Il mio nuovo foglio | F13: =COUNTIFS('Visualizations'!$A$7:$A$100000,A13,'Visualizations'!$B$7:$B$100000,C13) | G13: =COUNTIFS('Visualizations'!$A$7:$A$100000,A13,'Visualizations'!$B$7:$B$100000,C13,'Visualizations'!$H$7:$H$100000,"?*") | H13: 24 x 12
A14: TryConfigColorAndAgrField | B14: 1 | C14: yJByFm | D14: Visualizza dati | F14: =COUNTIFS('Visualizations'!$A$7:$A$100000,A14,'Visualizations'!$B$7:$B$100000,C14) | G14: =COUNTIFS('Visualizations'!$A$7:$A$100000,A14,'Visualizations'!$B$7:$B$100000,C14,'Visualizations'!$H$7:$H$100000,"?*") | H14: 24 x 12
A15: TryExtensions | B15: 1 | C15: bEBzp | D15: Hello World | F15: =COUNTIFS('Visualizations'!$A$7:$A$100000,A15,'Visualizations'!$B$7:$B$100000,C15) | G15: =COUNTIFS('Visualizations'!$A$7:$A$100000,A15,'Visualizations'!$B$7:$B$100000,C15,'Visualizations'!$H$7:$H$100000,"?*") | H15: 24 x 12
A16: Tutorial creazione nuova app | B16: 1 | C16: pNfY | D16: Dashboard | F16: =COUNTIFS('Visualizations'!$A$7:$A$100000,A16,'Visualizations'!$B$7:$B$100000,C16) | G16: =COUNTIFS('Visualizations'!$A$7:$A$100000,A16,'Visualizations'!$B$7:$B$100000,C16,'Visualizations'!$H$7:$H$100000,"?*") | H16: 24 x 12
A17: Tutorial creazione nuova app | B17: 2 | C17: DxxjRM | D17: Product details | F17: =COUNTIFS('Visualizations'!$A$7:$A$100000,A17,'Visualizations'!$B$7:$B$100000,C17) | G17: =COUNTIFS('Visualizations'!$A$7:$A$100000,A17,'Visualizations'!$B$7:$B$100000,C17,'Visualizations'!$H$7:$H$100000,"?*") | H17: 24 x 12
A18: Tutorial creazione nuova app | B18: 3 | C18: dwcu | D18: Customer details | F18: =COUNTIFS('Visualizations'!$A$7:$A$100000,A18,'Visualizations'!$B$7:$B$100000,C18) | G18: =COUNTIFS('Visualizations'!$A$7:$A$100000,A18,'Visualizations'!$B$7:$B$100000,C18,'Visualizations'!$H$7:$H$100000,"?*") | H18: 24 x 12
A19: Tutorial creazione nuova app | B19: 4 | C19: jnJmy | D19: Customer location | F19: =COUNTIFS('Visualizations'!$A$7:$A$100000,A19,'Visualizations'!$B$7:$B$100000,C19) | G19: =COUNTIFS('Visualizations'!$A$7:$A$100000,A19,'Visualizations'!$B$7:$B$100000,C19,'Visualizations'!$H$7:$H$100000,"?*") | H19: 24 x 12

Sheet Visualizations
C2: Visualizations · every object on every sheet
A5: =HYPERLINK("#'Discovery'!A1","« Back to Discovery") | B5: Every object on every sheet (including containers and filter panes): type, title, master visualization link, dimensions, measures, grid position.
A6: App | B6: Sheet ID | C6: Sheet | D6: Object ID | E6: Type | F6: Title | G6: Inside container | H6: Master visualization ID | I6: Master visualization | J6: Dimensions | K6: Measures | L6: # Dim | M6: # Meas | N6: Grid position
A7: Executive Dashboard | B7: PfKsJK | C7: KPI Dashboard | D7: KxdNL | E7: gauge | F7: 'Expenses vs. Target = ' & num(sum({<[Fiscal Year]={$(vYTDYear)}, _HistoryFlag={1}>} ExpenseActual)/sum({<[Fiscal Year]={$(vYTDYear)}, _HistoryFlag={1}>} ExpenseBudget), '#,##0%') | K7: Expenses vs. Target | L7: 0 | M7: 1 | N7: col 0, row 0, 8x4
A8: Executive Dashboard | B8: PfKsJK | C8: KPI Dashboard | D8: tcxTY | E8: gauge | F8: 'Revenue vs Last Year Revenue = '& num(Sum({<[Fiscal Year]={$(=vYTDYear)}, FiscalMonthNum={"<=$(vCurrentMonthNum)"}>}[Sales Price]*[Sales Quantity])/Sum({<[Fiscal Year]={$(=(vYTDYear)-1)}, FiscalMonthNum={"<=$(vCurrentMonthNum)"}>}[Sales Price]*[Sales Quantity]), '#,##0%') | K8: Revenue vs. LY Revenue | L8: 0 | M8: 1 | N8: col 8, row 0, 8x4
A9: Executive Dashboard | B9: PfKsJK | C9: KPI Dashboard | D9: MdpsUpA | E9: gauge | F9: 'Account Receivable Overdue = ' & num((Sum({<[Fiscal Year]={$(vYTDYear)}>} AROpen)-Sum({<[Fiscal Year]={$(vYTDYear)}>} ARCurrent))/Sum({<[Fiscal Year]={$(vYTDYear)}>} AROpen), '#,##0%') | K9: AR % Overdue | L9: 0 | M9: 1 | N9: col 16, row 0, 8x4
A10: Executive Dashboard | B10: PfKsJK | C10: KPI Dashboard | D10: NaKQwM | E10: piechart | F10: Expenses by Accounts | J10: Account | K10: Expense Amount | L10: 1 | M10: 1 | N10: col 0, row 4, 8x5
A11: Executive Dashboard | B11: PfKsJK | C11: KPI Dashboard | D11: ZxDKp | E11: piechart | F11: Revenue by Products | J11: Product Sub Group Desc | K11: Revenue | L11: 1 | M11: 1 | N11: col 8, row 4, 8x5
A12: Executive Dashboard | B12: PfKsJK | C12: KPI Dashboard | D12: ARNmpdM | E12: piechart | F12: Amount Overdue by Customers | J12: Customer | K12: Amount Overdue | L12: 1 | M12: 1 | N12: col 16, row 4, 8x5
A13: Executive Dashboard | B13: PfKsJK | C13: KPI Dashboard | D13: JEBdZz | E13: linechart | F13: Expense Trend | J13: Month | K13: Expense Amount | L13: 1 | M13: 1 | N13: col 0, row 9, 8x3
A14: Executive Dashboard | B14: PfKsJK | C14: KPI Dashboard | D14: GJxgd | E14: linechart | F14: Revenue Trend | J14: Month | K14: Revenue | L14: 1 | M14: 1 | N14: col 8, row 9, 8x3
A15: Executive Dashboard | B15: PfKsJK | C15: KPI Dashboard | D15: QYthJs | E15: linechart | F15: AR Trend | J15: Month | K15: AR Average Balance | L15: 1 | M15: 1 | N15: col 16, row 9, 8x3
A16: Executive Dashboard | B16: JsCeVm | C16: Account Receivable Analysis | D16: YPPUPE | E16: treemap | F16: Revenue by Sales Rep | J16: Segment; Sales Rep Name | K16: Revenue | L16: 2 | M16: 1 | N16: col 0, row 0, 6x12
A17: Executive Dashboard | B17: JsCeVm | C17: Account Receivable Analysis | D17: trePT | E17: gauge | K17: Margin % | L17: 0 | M17: 1 | N17: col 6, row 0, 3x4
A18: Executive Dashboard | B18: JsCeVm | C18: Account Receivable Analysis | D18: ZFaWvw | E18: gauge | K18: Days Sales Outstanding | L18: 0 | M18: 1 | N18: col 6, row 8, 3x4
A19: Executive Dashboard | B19: JsCeVm | C19: Account Receivable Analysis | D19: VARhxUj | E19: gauge | K19: AR % Overdue | L19: 0 | M19: 1 | N19: col 6, row 4, 3x4
A20: Executive Dashboard | B20: JsCeVm | C20: Account Receivable Analysis | D20: BmfQbz | E20: scatterplot | F20: Sales vs Margin | J20: Customer | K20: CY Sales; Margin % | L20: 1 | M20: 2 | N20: col 9, row 0, 8x4
A21: Executive Dashboard | B21: JsCeVm | C21: Account Receivable Analysis | D21: mVPztHm | E21: scatterplot | F21: Amount Overdue vs DSO | J21: Customer | K21: Days Sales Outstanding; Amount Overdue | L21: 1 | M21: 2 | N21: col 9, row 4, 8x4
A22: Executive Dashboard | B22: JsCeVm | C22: Account Receivable Analysis | D22: NeLVr | E22: scatterplot | F22: Avg Sales Per Day vs AR Avg Balance | J22: Customer | K22: AR Average Balance; Avg Sales Per Day | L22: 1 | M22: 2 | N22: col 9, row 8, 8x4
A23: Executive Dashboard | B23: JsCeVm | C23: Account Receivable Analysis | D23: nnkLtpf | E23: table | F23: CY Sales vs LY Sales | J23: Product | K23: CY Sales; LY Sales | L23: 1 | M23: 2 | N23: col 17, row 0, 7x12
A24: Executive Dashboard | B24: FaQeFa | C24: Sales Analysis | D24: fzrxtjq | E24: scatterplot | F24: Sales vs Margin by Sales Rep | J24: Sales Rep Name | K24: Margin %; Revenue | L24: 1 | M24: 2 | N24: col 0, row 1, 12x6
A25: Executive Dashboard | B25: FaQeFa | C25: Sales Analysis | D25: nvqpV | E25: linechart | F25: Average Sales Per Day | J25: Year Month | K25: Avg Sales Per Day | L25: 1 | M25: 1 | N25: col 0, row 7, 12x5
A26: Executive Dashboard | B26: FaQeFa | C26: Sales Analysis | D26: qZPdytp | E26: barchart | F26: 'Total Revenue by Product Group = ' & num(Sum([Sales Quantity]*[Sales Price]), '$#,##0') | J26: Product Sub Group Desc | K26: Revenue | L26: 1 | M26: 1 | N26: col 12, row 1, 12x11
A27: Executive Dashboard | B27: FaQeFa | C27: Sales Analysis | D27: jRMGQG | E27: filterpane | L27: 0 | M27: 0 | N27: col 0, row 0, 24x1
A28: Executive Dashboard | B28: FaQeFa | C28: Sales Analysis | D28: nURpk | E28: listbox | F28: Segment | G28: jRMGQG | J28: Segment | L28: 1 | M28: 0
A29: Executive Dashboard | B29: FaQeFa | C29: Sales Analysis | D29: pdLG | E29: listbox | F29: Region | G29: jRMGQG | J29: Region | L29: 1 | M29: 0
A30: Executive Dashboard | B30: FaQeFa | C30: Sales Analysis | D30: BArut | E30: listbox | F30: Sales Rep Name | G30: jRMGQG | J30: Sales Rep Name | L30: 1 | M30: 0
A31: Executive Dashboard | B31: FaQeFa | C31: Sales Analysis | D31: RdNtA | E31: listbox | F31: Product Group | G31: jRMGQG | J31: Product Group | L31: 1 | M31: 0
A32: Helpdesk Management | B32: VkcYvCR | C32: Case Details | D32: ycppXj | E32: filterpane | F32: Filters | L32: 0 | M32: 0 | N32: col 0, row 0, 24x1
A33: Helpdesk Management | B33: VkcYvCR | C33: Case Details | D33: dEDkpN | E33: listbox | F33: Cases Open/Closed | G33: ycppXj | J33: Cases Open/Closed | L33: 1 | M33: 0
A34: Helpdesk Management | B34: VkcYvCR | C34: Case Details | D34: pKBGKm | E34: listbox | F34: Priority | G34: ycppXj | J34: Priority | L34: 1 | M34: 0
A35: Helpdesk Management | B35: VkcYvCR | C35: Case Details | D35: JEPxkM | E35: listbox | F35: IT Resources | G35: ycppXj | J35: Case Owner | L35: 1 | M35: 0
A36: Helpdesk Management | B36: VkcYvCR | C36: Case Details | D36: WfWFp | E36: listbox | F36: Request Type | G36: ycppXj | J36: Case Record Type | L36: 1 | M36: 0
A37: Helpdesk Management | B37: VkcYvCR | C37: Case Details | D37: LZqevwG | E37: listbox | F37: Department | G37: ycppXj | J37: Case Owner Group | L37: 1 | M37: 0
A38: Helpdesk Management | B38: VkcYvCR | C38: Case Details | D38: rJFbvG | E38: table | F38: ='Case Details: ' & Num(Count(distinct %CaseId),'#,##0') & ' Cases' | J38: CaseNumber; Subject; Case Owner; Status; Case Created Date; Case Closed Date | K38: Case Duration (dd hh:mm) | L38: 6 | M38: 1 | N38: col 0, row 1, 24x11
A39: Helpdesk Management | B39: kHgmg | C39: Performance | D39: uETyGUP | E39: table | F39: Resource Details | J39: Case Owner; Status | K39: Tenure; Open Cases; Closed Cases; Total Cases; Open Cases - High; Open Cases - Medium; Open Cases - Low; Avg Case Duration | L39: 2 | M39: 8 | N39: col 0, row 6, 24x6
A40: Helpdesk Management | B40: kHgmg | C40: Performance | D40: xfvKMP | E40: linechart | F40: New Cases by Department over time | J40: YearMonth; Department | K40: Cumulative New Cases | L40: 2 | M40: 1 | N40: col 8, row 0, 16x6
A41: Helpdesk Management | B41: kHgmg | C41: Performance | D41: PAppmU | E41: piechart | F41: Open Cases by Age | J41: Case Timetable | K41: Open Cases | L41: 1 | M41: 1 | N41: col 0, row 0, 8x6
A42: Helpdesk Management | B42: 1ff88551-9c4d-41e0-b790-37f4c11d3df8 | C42: Dashboard | D42: a5e0f12c-38f5-4da9-8f3f-0e4566b28398 | E42: barchart | F42: Avg Case Resolution Time (Days) | J42: Case Owner Group | K42: Avg Case Duration | L42: 1 | M42: 1 | N42: col 16, row 0, 8x7
A43: Helpdesk Management | B43: 1ff88551-9c4d-41e0-b790-37f4c11d3df8 | C43: Dashboard | D43: 298bbd6d-f23d-4469-94a2-df243d680e0c | E43: scatterplot | F43: Open Cases vs Duration | J43: Case Owner | K43: Avg Case Duration; Open Cases | L43: 1 | M43: 2 | N43: col 5, row 0, 11x7
A44: Helpdesk Management | B44: 1ff88551-9c4d-41e0-b790-37f4c11d3df8 | C44: Dashboard | D44: hRZaKk | E44: linechart | F44: Open & Resolved Cases Over Time | J44: Date | K44: Cumulative New Cases; Cumulative Closed Cases | L44: 1 | M44: 2 | N44: col 5, row 7, 19x5
A45: Helpdesk Management | B45: 1ff88551-9c4d-41e0-b790-37f4c11d3df8 | C45: Dashboard | D45: RuTpzNW | E45: kpi | K45: High Priority Cases | L45: 0 | M45: 1 | N45: col 0, row 0, 5x4
A46: Helpdesk Management | B46: 1ff88551-9c4d-41e0-b790-37f4c11d3df8 | C46: Dashboard | D46: JARjh | E46: kpi | K46: Medium Priority Cases | L46: 0 | M46: 1 | N46: col 0, row 4, 5x4
A47: Helpdesk Management | B47: 1ff88551-9c4d-41e0-b790-37f4c11d3df8 | C47: Dashboard | D47: JsVPe | E47: kpi | K47: Low Priority Cases | L47: 0 | M47: 1 | N47: col 0, row 8, 5x4
A48: Sales Analysis | B48: RpwpQEp | C48: Il mio nuovo foglio | D48: sbVLvau | E48: barchart | J48: Category | K48: Sales | L48: 1 | M48: 1 | N48: col 0, row 0, 12x12
A49: Sales Analysis | B49: RpwpQEp | C49: Il mio nuovo foglio | D49: TbfcPf | E49: kpi | L49: 0 | M49: 0 | N49: col 12, row 0, 12x6
A50: TryConfigColorAndAgrField | B50: yJByFm | C50: Visualizza dati | D50: HAKV | E50: barchart | F50: Dati | J50: Prodotto | K50: Prezzo | L50: 1 | M50: 1 | N50: col 5, row 0, 19x6
A51: TryConfigColorAndAgrField | B51: yJByFm | C51: Visualizza dati | D51: VmJEtn | E51: filterpane | L51: 0 | M51: 0 | N51: col 0, row 0, 5x3
A52: TryConfigColorAndAgrField | B52: yJByFm | C52: Visualizza dati | D52: jmQRDRK | E52: listbox | F52: Tipo Prezzo | G52: VmJEtn | J52: DescTipoPrezzo | L52: 1 | M52: 0
A53: TryExtensions | B53: bEBzp | C53: Hello World | D53: PebMUH | E53: HelloWorld | L53: 0 | M53: 0 | N53: col 0, row 0, 12x12
A54: Tutorial creazione nuova app | B54: pNfY | C54: Dashboard | D54: pzU | E54: filterpane | H54: rmBWDa | I54: Period | L54: 0 | M54: 0 | N54: col 0, row 0, 4x4
A55: Tutorial creazione nuova app | B55: pNfY | C55: Dashboard | D55: pnMDWX | E55: filterpane | H55: ZvUFrB | I55: Region | L55: 0 | M55: 0 | N55: col 0, row 6, 4x6
A56: Tutorial creazione nuova app | B56: pNfY | C56: Dashboard | D56: ydBXqP | E56: piechart | F56: Sales per Region | J56: Region | K56: Sales | L56: 1 | M56: 1 | N56: col 4, row 0, 8x4
A57: Tutorial creazione nuova app | B57: pNfY | C57: Dashboard | D57: ceJJpM | E57: barchart | F57: Top 5 customers | J57: Customer | K57: Sales | L57: 1 | M57: 1 | N57: col 4, row 4, 8x4
A58: Tutorial creazione nuova app | B58: pNfY | C58: Dashboard | D58: KgbDMp | E58: combochart | J58: MonthYear | K58: Sales; Margin Percent | L58: 1 | M58: 2 | N58: col 4, row 8, 20x4
A59: Tutorial creazione nuova app | B59: pNfY | C59: Dashboard | D59: cqkwuD | E59: kpi | F59: Vendite totali e margine | K59: Sales; Sum(Margin) | L59: 0 | M59: 2 | N59: col 12, row 0, 6x3
A60: Tutorial creazione nuova app | B60: pNfY | C60: Dashboard | D60: Agtgjbq | E60: gauge | F60: Profit margin | K60: Margin Percent | L60: 0 | M60: 1 | N60: col 18, row 0, 6x3
A61: Tutorial creazione nuova app | B61: pNfY | C61: Dashboard | D61: fLTdzY | E61: linechart | F61: Quarterly trend | J61: Quarter; Year | K61: Sales | L61: 2 | M61: 1 | N61: col 12, row 3, 12x5
A62: Tutorial creazione nuova app | B62: DxxjRM | C62: Product details | D62: jUKT | E62: filterpane | H62: rmBWDa | I62: Period | L62: 0 | M62: 0 | N62: col 0, row 0, 4x4
A63: Tutorial creazione nuova app | B63: DxxjRM | C63: Product details | D63: UsusUz | E63: filterpane | H63: ZvUFrB | I63: Region | L63: 0 | M63: 0 | N63: col 0, row 6, 4x6
A64: Tutorial creazione nuova app | B64: DxxjRM | C64: Product details | D64: cqdV | E64: barchart | F64: ='Total sales ($):' & Round(Sum(Sales)/1000000, 0.1) & 'M' | J64: Product Group | K64: Sales; Margin | L64: 1 | M64: 2 | N64: col 4, row 0, 20x4
A65: Tutorial creazione nuova app | B65: DxxjRM | C65: Product details | D65: pKWxgrw | E65: treemap | F65: Product treemap | J65: Product Group; Product Type; Item Desc | K65: Sales | L65: 3 | M65: 1 | N65: col 4, row 4, 20x8
A66: Tutorial creazione nuova app | B66: dwcu | C66: Customer details | D66: HPTU | E66: filterpane | H66: rmBWDa | I66: Period | L66: 0 | M66: 0 | N66: col 0, row 0, 4x4
A67: Tutorial creazione nuova app | B67: dwcu | C67: Customer details | D67: qjmsvy | E67: filterpane | H67: ZJhRsc | I67: Manager | L67: 0 | M67: 0 | N67: col 0, row 5, 4x7
A68: Tutorial creazione nuova app | B68: dwcu | C68: Customer details | D68: CaFe | E68: scatterplot | J68: Customer | K68: Sales; Quantity | L68: 1 | M68: 2 | N68: col 4, row 0, 20x5
A69: Tutorial creazione nuova app | B69: dwcu | C69: Customer details | D69: bJvxeAh | E69: pivot-table | F69: Customer KPIs | J69: Customer; Product Group; Product Type | K69: Sales; Quantity; Margin Percent; # of Invoices; Average Sales per Invoice | L69: 3 | M69: 5 | N69: col 4, row 5, 20x7
A70: Tutorial creazione nuova app | B70: jnJmy | C70: Customer location | D70: VzycV | E70: filterpane | H70: ZvUFrB | I70: Region | L70: 0 | M70: 0 | N70: col 0, row 0, 4x4
A71: Tutorial creazione nuova app | B71: jnJmy | C71: Customer location | D71: MsfSMgj | E71: filterpane | H71: GbHREb | I71: City | L71: 0 | M71: 0 | N71: col 0, row 4, 4x8
A72: Tutorial creazione nuova app | B72: jnJmy | C72: Customer location | D72: grYjvzB | E72: filterpane | H72: LsAsQkp | I72: Customer | L72: 0 | M72: 0 | N72: col 4, row 0, 4x12
A73: Tutorial creazione nuova app | B73: jnJmy | C73: Customer location | D73: qbVaPgL | E73: map | F73: Location | J73: City; Location | K73: Sales | L73: 2 | M73: 1 | N73: col 8, row 0, 16x9

Sheet MasterMeasures
C2: Master measures · the measure libraries
A5: =HYPERLINK("#'Discovery'!A1","« Back to Discovery") | B5: Library measures with the full expression, complexity flags and how often they are used.
A6: App | B6: ID | C6: Label | D6: Expression | E6: Description | F6: Tags | G6: Set analysis | H6: Aggr() | I6: If / Pick / Match | J6: $() expansion | K6: Complexity | L6: Used in visualizations | M6: Expression length | N6: Found by
A7: Executive Dashboard | B7: NPPsJt | C7: Revenue | D7: Sum([Sales Quantity]*[Sales Price]) | E7: The revenue. | G7: No | H7: No | I7: No | J7: No | K7: Low | L7: =COUNTIFS('MasterItemUsage'!$A$7:$A$100000,A7,'MasterItemUsage'!$F$7:$F$100000,B7) | M7: 35 | N7: qlik-parser
A8: Executive Dashboard | B8: SLJUwQj | C8: Sales Quantity | D8: Sum([Sales Quantity]) | E8: The quantity sold. | G8: No | H8: No | I8: No | J8: No | K8: Low | L8: =COUNTIFS('MasterItemUsage'!$A$7:$A$100000,A8,'MasterItemUsage'!$F$7:$F$100000,B8) | M8: 21 | N8: qlik-parser
A9: Executive Dashboard | B9: mwwzJ | C9: Expenses vs. Target | D9: sum({<[Fiscal Year]={$(vYTDYear)}, _HistoryFlag={1}>} ExpenseActual)/sum({<[Fiscal Year]={$(vYTDYear)}, _HistoryFlag={1}>} ExpenseBudget) | E9: Ratio of actual expenses compared to the target expenses. | G9: Yes | H9: No | I9: No | J9: Yes | K9: Medium | L9: =COUNTIFS('MasterItemUsage'!$A$7:$A$100000,A9,'MasterItemUsage'!$F$7:$F$100000,B9) | M9: 137 | N9: qlik-parser
A10: Executive Dashboard | B10: bUft | C10: Expense as % of Sale | D10: If(Sum(ExpenseActual)>0,Sum(ExpenseActual),0) | E10: Actual expenses. | G10: No | H10: No | I10: Yes | J10: No | K10: Medium | L10: =COUNTIFS('MasterItemUsage'!$A$7:$A$100000,A10,'MasterItemUsage'!$F$7:$F$100000,B10) | M10: 45 | N10: qlik-parser
A11: Executive Dashboard | B11: napvtJ | C11: Expense Amount | D11: sum(ExpenseActual) | E11: Expenses. | G11: No | H11: No | I11: No | J11: No | K11: Low | L11: =COUNTIFS('MasterItemUsage'!$A$7:$A$100000,A11,'MasterItemUsage'!$F$7:$F$100000,B11) | M11: 18 | N11: qlik-parser
A12: Executive Dashboard | B12: jpcvPf | C12: Expense (New Calculation) | D12: Sum({<[Fiscal Year]={$(vYear)}>}ExpenseActual)/1000 | E12: Expenses in thousands. | G12: Yes | H12: No | I12: No | J12: Yes | K12: Medium | L12: =COUNTIFS('MasterItemUsage'!$A$7:$A$100000,A12,'MasterItemUsage'!$F$7:$F$100000,B12) | M12: 51 | N12: qlik-parser
A13: Executive Dashboard | B13: FDPQYx | C13: AR % Overdue | D13: (Sum({<[Fiscal Year]={$(vYTDYear)}>} AROpen)-Sum({<[Fiscal Year]={$(vYTDYear)}>} ARCurrent))/Sum({<[Fiscal Year]={$(vYTDYear)}>} AROpen) | E13: The percentage overdue year to date. | G13: Yes | H13: No | I13: No | J13: Yes | K13: Medium | L13: =COUNTIFS('MasterItemUsage'!$A$7:$A$100000,A13,'MasterItemUsage'!$F$7:$F$100000,B13) | M13: 136 | N13: qlik-parser
A14: Executive Dashboard | B14: w | C14: Inventory Amount | D14: Sum(StockOH*CostPrice) | E14: The amount in inventory ($). | G14: No | H14: No | I14: No | J14: No | K14: Low | L14: =COUNTIFS('MasterItemUsage'!$A$7:$A$100000,A14,'MasterItemUsage'!$F$7:$F$100000,B14) | M14: 22 | N14: qlik-parser
A15: Executive Dashboard | B15: sgeyqn | C15: Margin Amount | D15: (Sum([Sales Quantity]*[Sales Price])) - (Sum([Sales Cost Amount])) | E15: The margin amount. | G15: No | H15: No | I15: No | J15: No | K15: Low | L15: =COUNTIFS('MasterItemUsage'!$A$7:$A$100000,A15,'MasterItemUsage'!$F$7:$F$100000,B15) | M15: 66 | N15: qlik-parser
A16: Executive Dashboard | B16: RRcCqu | C16: # of Cust AR60+ | D16: if( Sum ([AR60+])>0, count ( distinct [Customer Number])) | E16: Number of customers overdue by 60 or more days. | G16: No | H16: No | I16: Yes | J16: No | K16: Medium | L16: =COUNTIFS('MasterItemUsage'!$A$7:$A$100000,A16,'MasterItemUsage'!$F$7:$F$100000,B16) | M16: 57 | N16: qlik-parser
A17: Executive Dashboard | B17: jnjgaPY | C17: Cost (Total) | D17: Sum([Sales Cost Amount]) | E17: Cost amount. | G17: No | H17: No | I17: No | J17: No | K17: Low | L17: =COUNTIFS('MasterItemUsage'!$A$7:$A$100000,A17,'MasterItemUsage'!$F$7:$F$100000,B17) | M17: 24 | N17: qlik-parser
A18: Executive Dashboard | B18: pVTm | C18: AR Average Balance | D18: Sum (ARAvgBal) | E18: Average account receivables balance. | G18: No | H18: No | I18: No | J18: No | K18: Low | L18: =COUNTIFS('MasterItemUsage'!$A$7:$A$100000,A18,'MasterItemUsage'!$F$7:$F$100000,B18) | M18: 14 | N18: qlik-parser
... A55: Helpdesk Management | B55: NRbtFne | C55: Most Cases | D55: firstsortedvalue( Priority, -Aggr(Count({<[Cases Open/Closed]={'Open Cases'}>}Distinct [%CaseId] ),[Case Owner Group],Priority)) | E55: The priority group with the most open cases. | G55: Yes | H55: Yes | I55: No | J55: No | K55: High | L55: =COUNTIFS('MasterItemUsage'!$A$7:$A$100000,A55,'MasterItemUsage'!$F$7:$F$100000,B55) | M55: 128 | N55: qlik-parser
A56: Tutorial creazione nuova app | B56: pHjKV | C56: Sales | D56: Sum(Sales) | G56: No | H56: No | I56: No | J56: No | K56: Low | L56: =COUNTIFS('MasterItemUsage'!$A$7:$A$100000,A56,'MasterItemUsage'!$F$7:$F$100000,B56) | M56: 10 | N56: qlik-parser
A57: Tutorial creazione nuova app | B57: SKnVL | C57: Margin Percent | D57: (Sum(Sales) - Sum(Cost)) / Sum(Sales) | G57: No | H57: No | I57: No | J57: No | K57: Low | L57: =COUNTIFS('MasterItemUsage'!$A$7:$A$100000,A57,'MasterItemUsage'!$F$7:$F$100000,B57) | M57: 37 | N57: qlik-parser
A58: Tutorial creazione nuova app | B58: xNwJu | C58: Margin | D58: Sum(Margin) | G58: No | H58: No | I58: No | J58: No | K58: Low | L58: =COUNTIFS('MasterItemUsage'!$A$7:$A$100000,A58,'MasterItemUsage'!$F$7:$F$100000,B58) | M58: 11 | N58: qlik-parser
A59: Tutorial creazione nuova app | B59: CdSMz | C59: Quantity | D59: Sum([Sales Qty]) | G59: No | H59: No | I59: No | J59: No | K59: Low | L59: =COUNTIFS('MasterItemUsage'!$A$7:$A$100000,A59,'MasterItemUsage'!$F$7:$F$100000,B59) | M59: 16 | N59: qlik-parser
A60: Tutorial creazione nuova app | B60: LsPLsq | C60: # of Invoices | D60: Count(Distinct([Invoice Number])) | G60: No | H60: No | I60: No | J60: No | K60: Low | L60: =COUNTIFS('MasterItemUsage'!$A$7:$A$100000,A60,'MasterItemUsage'!$F$7:$F$100000,B60) | M60: 33 | N60: qlik-parser
A61: Tutorial creazione nuova app | B61: VaEaEf | C61: Average Sales per Invoice | D61: Sum(Sales)/Count(Distinct([Invoice Number])) | G61: No | H61: No | I61: No | J61: No | K61: Low | L61: =COUNTIFS('MasterItemUsage'!$A$7:$A$100000,A61,'MasterItemUsage'!$F$7:$F$100000,B61) | M61: 44 | N61: qlik-parser

Sheet MasterDimensions
C2: Master dimensions · the dimension libraries
A5: =HYPERLINK("#'Discovery'!A1","« Back to Discovery") | B5: Library dimensions: fields, single or drill-down, usage.
A6: App | B6: ID | C6: Label | D6: Fields | E6: Kind | F6: Description | G6: Tags | H6: Used in visualizations | I6: Found by
A7: Executive Dashboard | B7: EzubBQ | C7: Customer Number | D7: Customer Number | E7: Single | H7: =COUNTIFS('MasterItemUsage'!$A$7:$A$100000,A7,'MasterItemUsage'!$F$7:$F$100000,B7) | I7: qlik-parser
A8: Executive Dashboard | B8: XFhtUb | C8: Sales Rep Name | D8: Sales Rep Name | E8: Single | H8: =COUNTIFS('MasterItemUsage'!$A$7:$A$100000,A8,'MasterItemUsage'!$F$7:$F$100000,B8) | I8: qlik-parser
A9: Executive Dashboard | B9: ANYTpUm | C9: Product Type Desc | D9: Product Type Desc | E9: Single | G9: Product Hierarchy | H9: =COUNTIFS('MasterItemUsage'!$A$7:$A$100000,A9,'MasterItemUsage'!$F$7:$F$100000,B9) | I9: qlik-parser
A10: Executive Dashboard | B10: pmresb | C10: Product | D10: Line Desc 1 | E10: Single | G10: Product Hierarchy | H10: =COUNTIFS('MasterItemUsage'!$A$7:$A$100000,A10,'MasterItemUsage'!$F$7:$F$100000,B10) | I10: qlik-parser
A11: Executive Dashboard | B11: rAWLLGj | C11: Product Group | D11: Product Group Desc | E11: Single | G11: Product Hierarchy | H11: =COUNTIFS('MasterItemUsage'!$A$7:$A$100000,A11,'MasterItemUsage'!$F$7:$F$100000,B11) | I11: qlik-parser
A12: Executive Dashboard | B12: PjEUh | C12: Order Number | D12: Order Number | E12: Single | H12: =COUNTIFS('MasterItemUsage'!$A$7:$A$100000,A12,'MasterItemUsage'!$F$7:$F$100000,B12) | I12: qlik-parser
A13: Executive Dashboard | B13: nrxFRV | C13: Account Group | D13: AccountGroupDesc | E13: Single | H13: =COUNTIFS('MasterItemUsage'!$A$7:$A$100000,A13,'MasterItemUsage'!$F$7:$F$100000,B13) | I13: qlik-parser
A14: Executive Dashboard | B14: jgxpDbw | C14: Region | D14: Region | E14: Single | H14: =COUNTIFS('MasterItemUsage'!$A$7:$A$100000,A14,'MasterItemUsage'!$F$7:$F$100000,B14) | I14: qlik-parser
A15: Executive Dashboard | B15: HnEfUp | C15: Year Month | D15: YYYYMM | E15: Single | H15: =COUNTIFS('MasterItemUsage'!$A$7:$A$100000,A15,'MasterItemUsage'!$F$7:$F$100000,B15) | I15: qlik-parser
A16: Executive Dashboard | B16: DcuPcq | C16: Product Sub Group Desc | D16: Product Sub Group Desc | E16: Single | F16: Product sub group description | G16: Product Hierarchy | H16: =COUNTIFS('MasterItemUsage'!$A$7:$A$100000,A16,'MasterItemUsage'!$F$7:$F$100000,B16) | I16: qlik-parser
A17: Executive Dashboard | B17: aLVsP | C17: Account | D17: AccountDesc | E17: Single | F17: Account description. | H17: =COUNTIFS('MasterItemUsage'!$A$7:$A$100000,A17,'MasterItemUsage'!$F$7:$F$100000,B17) | I17: qlik-parser
A18: Executive Dashboard | B18: pcZcGjn | C18: Customer | D18: Customer | E18: Single | H18: =COUNTIFS('MasterItemUsage'!$A$7:$A$100000,A18,'MasterItemUsage'!$F$7:$F$100000,B18) | I18: qlik-parser
A19: Executive Dashboard | B19: RJRD | C19: ARAge | D19: ARAge | E19: Single | F19: Age of account receivable. | H19: =COUNTIFS('MasterItemUsage'!$A$7:$A$100000,A19,'MasterItemUsage'!$F$7:$F$100000,B19) | I19: qlik-parser
A20: Executive Dashboard | B20: jcDdm | C20: Order Status | D20: Order Status | E20: Single | H20: =COUNTIFS('MasterItemUsage'!$A$7:$A$100000,A20,'MasterItemUsage'!$F$7:$F$100000,B20) | I20: qlik-parser
A21: Executive Dashboard | B21: AswNnUE | C21: Year | D21: Fiscal Year | E21: Single | H21: =COUNTIFS('MasterItemUsage'!$A$7:$A$100000,A21,'MasterItemUsage'!$F$7:$F$100000,B21) | I21: qlik-parser
A22: Executive Dashboard | B22: FYkzzR | C22: Customer Type | D22: Customer Type | E22: Single | H22: =COUNTIFS('MasterItemUsage'!$A$7:$A$100000,A22,'MasterItemUsage'!$F$7:$F$100000,B22) | I22: qlik-parser
A23: Executive Dashboard | B23: wLJmmJn | C23: Segment | D23: SegmentDesc | E23: Single | H23: =COUNTIFS('MasterItemUsage'!$A$7:$A$100000,A23,'MasterItemUsage'!$F$7:$F$100000,B23) | I23: qlik-parser
A24: Executive Dashboard | B24: eMukN | C24: Quarter | D24: Fiscal Quarter | E24: Single | H24: =COUNTIFS('MasterItemUsage'!$A$7:$A$100000,A24,'MasterItemUsage'!$F$7:$F$100000,B24) | I24: qlik-parser
A25: Executive Dashboard | B25: dyCEjG | C25: Month | D25: FiscalMonth | E25: Single | H25: =COUNTIFS('MasterItemUsage'!$A$7:$A$100000,A25,'MasterItemUsage'!$F$7:$F$100000,B25) | I25: qlik-parser
A26: Executive Dashboard | B26: jxuDwx | C26: Inventory Turns | D26: ClassTurns | E26: Single | F26: The number of times inventory is sold or used in a year. | H26: =COUNTIFS('MasterItemUsage'!$A$7:$A$100000,A26,'MasterItemUsage'!$F$7:$F$100000,B26) | I26: qvf-app
A27: Executive Dashboard | B27: QuWSp | C27: Account Drill | D27: AccountDesc, AccountGroupDesc | E27: Drill-down | F27: Drill down from the account description to the account group description. | H27: =COUNTIFS('MasterItemUsage'!$A$7:$A$100000,A27,'MasterItemUsage'!$F$7:$F$100000,B27) | I27: qvf-app
A28: Helpdesk Management | B28: wpUyjc | C28: Cases Open/Closed | D28: Cases Open/Closed | E28: Single | F28: Open and closed cases. | H28: =COUNTIFS('MasterItemUsage'!$A$7:$A$100000,A28,'MasterItemUsage'!$F$7:$F$100000,B28) | I28: qlik-parser
A29: Helpdesk Management | B29: RBBKJP | C29: Department | D29: Case Owner Group | E29: Single | H29: =COUNTIFS('MasterItemUsage'!$A$7:$A$100000,A29,'MasterItemUsage'!$F$7:$F$100000,B29) | I29: qlik-parser
A30: Helpdesk Management | B30: hyeGht | C30: Priority | D30: Priority | E30: Single | F30: Case priority. | H30: =COUNTIFS('MasterItemUsage'!$A$7:$A$100000,A30,'MasterItemUsage'!$F$7:$F$100000,B30) | I30: qlik-parser
A31: Helpdesk Management | B31: Bbdkpp | C31: Request Type | D31: Case Record Type | E31: Single | F31: Type of helpdesk request. | H31: =COUNTIFS('MasterItemUsage'!$A$7:$A$100000,A31,'MasterItemUsage'!$F$7:$F$100000,B31) | I31: qlik-parser
A32: Helpdesk Management | B32: krpjsE | C32: %OwnerId | D32: %OwnerId | E32: Single | F32: The Owner ID. | H32: =COUNTIFS('MasterItemUsage'!$A$7:$A$100000,A32,'MasterItemUsage'!$F$7:$F$100000,B32) | I32: qlik-parser
A33: Helpdesk Management | B33: rfQk | C33: IT Resources | D33: Case Owner | E33: Single | F33: IT resource. | H33: =COUNTIFS('MasterItemUsage'!$A$7:$A$100000,A33,'MasterItemUsage'!$F$7:$F$100000,B33) | I33: qlik-parser
A34: Helpdesk Management | B34: sEavA | C34: %CaseId | D34: %CaseId | E34: Single | F34: The Case ID. | H34: =COUNTIFS('MasterItemUsage'!$A$7:$A$100000,A34,'MasterItemUsage'!$F$7:$F$100000,B34) | I34: qlik-parser
A35: Helpdesk Management | B35: jySjA | C35: Year | D35: Year | E35: Single | H35: =COUNTIFS('MasterItemUsage'!$A$7:$A$100000,A35,'MasterItemUsage'!$F$7:$F$100000,B35) | I35: qlik-parser

Sheet MasterVisualizations
C2: Master visualizations · reusable charts
A5: =HYPERLINK("#'Discovery'!A1","« Back to Discovery") | B5: Reusable library charts with their dimensions, measures and usage.
A6: App | B6: ID | C6: Title | D6: Chart type | E6: Description | F6: Dimensions | G6: Measures | H6: Used on sheets
A7: Executive Dashboard | B7: tmaqpf | C7: Revenue by Product | D7: treemap | E7: View revenue by product. | F7: Product | G7: Revenue | H7: =COUNTIFS('MasterItemUsage'!$A$7:$A$100000,A7,'MasterItemUsage'!$F$7:$F$100000,B7)
A8: Executive Dashboard | B8: JZMrdb | C8: Product Inventory Turns, Amount and Margin% | D8: table | E8: Products in inventory and their dollar value, margin and number of inventory turns. | F8: Product; Inventory Turns | G8: Inventory Amount; Margin % | H8: =COUNTIFS('MasterItemUsage'!$A$7:$A$100000,A8,'MasterItemUsage'!$F$7:$F$100000,B8)
A9: Executive Dashboard | B9: BHTXyNM | C9: Expenses as % Sales | D9: piechart | E9: The expenses as a percentage of the sales. | F9: Account | G9: Expenses % of Sales | H9: =COUNTIFS('MasterItemUsage'!$A$7:$A$100000,A9,'MasterItemUsage'!$F$7:$F$100000,B9)
A10: Executive Dashboard | B10: pDKRhr | C10: Customer Revenue vs. Expense | D10: scatterplot | E10: Correlation between customer revenue and expense amount. | F10: Customer | G10: Expense Amount; Revenue | H10: =COUNTIFS('MasterItemUsage'!$A$7:$A$100000,A10,'MasterItemUsage'!$F$7:$F$100000,B10)
A11: Executive Dashboard | B11: FDJPm | C11: Cost Center Report (000s) | D11: table | E11: Expense details such as Account Group, account, Expenses and Budget. | F11: Account Group; Account | G11: Expense 2012; Budget; Expenses 2013 | H11: =COUNTIFS('MasterItemUsage'!$A$7:$A$100000,A11,'MasterItemUsage'!$F$7:$F$100000,B11)
A12: Executive Dashboard | B12: nRxXG | C12: Onhand Inventory $ (sorted by Sales Qty) | D12: barchart | E12: Inventory that is available to be sold. | F12: Product | G12: Inventory Amount | H12: =COUNTIFS('MasterItemUsage'!$A$7:$A$100000,A12,'MasterItemUsage'!$F$7:$F$100000,B12)
A13: Tutorial creazione nuova app | B13: rmBWDa | C13: Period | D13: filterpane | H13: =COUNTIFS('MasterItemUsage'!$A$7:$A$100000,A13,'MasterItemUsage'!$F$7:$F$100000,B13)
A14: Tutorial creazione nuova app | B14: ZvUFrB | C14: Region | D14: filterpane | H14: =COUNTIFS('MasterItemUsage'!$A$7:$A$100000,A14,'MasterItemUsage'!$F$7:$F$100000,B14)
A15: Tutorial creazione nuova app | B15: ZJhRsc | C15: Manager | D15: filterpane | H15: =COUNTIFS('MasterItemUsage'!$A$7:$A$100000,A15,'MasterItemUsage'!$F$7:$F$100000,B15)
A16: Tutorial creazione nuova app | B16: GbHREb | C16: City | D16: filterpane | H16: =COUNTIFS('MasterItemUsage'!$A$7:$A$100000,A16,'MasterItemUsage'!$F$7:$F$100000,B16)
A17: Tutorial creazione nuova app | B17: LsAsQkp | C17: Customer | D17: filterpane | H17: =COUNTIFS('MasterItemUsage'!$A$7:$A$100000,A17,'MasterItemUsage'!$F$7:$F$100000,B17)

Sheet MasterItemUsage
C2: Master item usage · which visualization uses which master item
A5: =HYPERLINK("#'Discovery'!A1","« Back to Discovery") | B5: One row per link from a visualization to a master item; feeds the usage counts.
A6: App | B6: Visualization ID | C6: Visualization type | D6: Sheet | E6: Master item kind | F6: Master item ID | G6: Master item
A7: Executive Dashboard | B7: KxdNL | C7: gauge | D7: KPI Dashboard | E7: Master measure | F7: mwwzJ | G7: Expenses vs. Target
A8: Executive Dashboard | B8: tcxTY | C8: gauge | D8: KPI Dashboard | E8: Master measure | F8: STSDYR | G8: Revenue vs. LY Revenue
A9: Executive Dashboard | B9: MdpsUpA | C9: gauge | D9: KPI Dashboard | E9: Master measure | F9: FDPQYx | G9: AR % Overdue
A10: Executive Dashboard | B10: NaKQwM | C10: piechart | D10: KPI Dashboard | E10: Master dimension | F10: aLVsP | G10: Account
A11: Executive Dashboard | B11: NaKQwM | C11: piechart | D11: KPI Dashboard | E11: Master measure | F11: napvtJ | G11: Expense Amount
A12: Executive Dashboard | B12: ZxDKp | C12: piechart | D12: KPI Dashboard | E12: Master dimension | F12: DcuPcq | G12: Product Sub Group Desc
A13: Executive Dashboard | B13: ZxDKp | C13: piechart | D13: KPI Dashboard | E13: Master measure | F13: NPPsJt | G13: Revenue
A14: Executive Dashboard | B14: ARNmpdM | C14: piechart | D14: KPI Dashboard | E14: Master dimension | F14: pcZcGjn | G14: Customer
A15: Executive Dashboard | B15: ARNmpdM | C15: piechart | D15: KPI Dashboard | E15: Master measure | F15: vLRMZz | G15: Amount Overdue
A16: Executive Dashboard | B16: JEBdZz | C16: linechart | D16: KPI Dashboard | E16: Master dimension | F16: dyCEjG | G16: Month
A17: Executive Dashboard | B17: JEBdZz | C17: linechart | D17: KPI Dashboard | E17: Master measure | F17: napvtJ | G17: Expense Amount
... A111: Tutorial creazione nuova app | B111: qbVaPgL | C111: map | D111: Customer location | E111: Master measure | F111: pHjKV | G111: Sales

Sheet Variables
C2: Variables · script and user variables
A5: =HYPERLINK("#'Discovery'!A1","« Back to Discovery") | B5: Script and user variables, their definitions and whether they are expressions.
A6: App | B6: Name | C6: Definition | D6: Comment | E6: Value | F6: Is expression (=) | G6: Script created | H6: List | I6: ID | J6: Found by
A7: Executive Dashboard | B7: CD | C7: D: | E7: NaN | F7: No | G7: Yes | H7: qvapp_variablelist | I7: 8ebc9e1d-55c2-453f-8e61-1f5e86abb831 | J7: qvf-app
A8: Executive Dashboard | B8: QvPath | C8: C:\Users\cbo\Downloads | E8: NaN | F8: No | G8: Yes | H8: qvapp_variablelist | I8: 746b2cd9-ce56-49a4-8bc5-76bb7c6dd788 | J8: qvf-app
A9: Executive Dashboard | B9: QvRoot | C9: C: | E9: NaN | F9: No | G9: Yes | H9: qvapp_variablelist | I9: 3ceede56-2ab6-46fa-a484-5e24ba7397c3 | J9: qvf-app
A10: Executive Dashboard | B10: QvWorkPath | C10: C:/Users/cbo/Documents/Qlik/QlikView/Apps | E10: NaN | F10: No | G10: Yes | H10: qvapp_variablelist | I10: 9d1ea17f-279e-4027-8d70-efb768ada910 | J10: qvf-app
A11: Executive Dashboard | B11: QvWorkRoot | C11: C: | E11: NaN | F11: No | G11: Yes | H11: qvapp_variablelist | I11: 1fff8abb-95e0-472b-9df7-6b425ed931eb | J11: qvf-app
A12: Executive Dashboard | B12: WinPath | C12: C:\Windows | E12: NaN | F12: No | G12: Yes | H12: qvapp_variablelist | I12: 8a7d43e5-a38e-492f-bdad-e722c5b36285 | J12: qvf-app
A13: Executive Dashboard | B13: WinRoot | C13: C: | E13: NaN | F13: No | G13: Yes | H13: qvapp_variablelist | I13: 52aa1e48-8073-4734-a953-555e898549a0 | J13: qvf-app
A14: Executive Dashboard | B14: ErrorMode | E14: 1 | F14: No | G14: Yes | H14: qvapp_variablelist | I14: bcee93bf-0c51-4542-acc1-049e6bba0655 | J14: qvf-app
A15: Executive Dashboard | B15: StripComments | E15: 1 | F15: No | G15: Yes | H15: qvapp_variablelist | I15: 216bafe6-fe53-4fd0-acef-ebd0e10ed759 | J15: qvf-app
A16: Executive Dashboard | B16: OpenUrlTimeout | E16: 86400 | F16: No | G16: Yes | H16: qvapp_variablelist | I16: 9ed380d2-e9d5-4419-9486-d497be948e37 | J16: qvf-app
A17: Executive Dashboard | B17: ScriptErrorCount | C17: 0 | E17: 0 | F17: No | G17: Yes | H17: qvapp_variablelist | I17: 850fa7eb-68af-44a3-8bf7-eaeadfdd42d2 | J17: qvf-app
A18: Executive Dashboard | B18: ScriptErrorList | E18: NaN | F18: No | G18: Yes | H18: qvapp_variablelist | I18: 39193e79-7c97-4d9c-b90d-bcf1ebbe7bf0 | J18: qvf-app
A19: Executive Dashboard | B19: ScriptError | E19: 0 | F19: No | G19: Yes | H19: qvapp_variablelist | I19: 1ec56f5d-a22e-4608-a045-9f492fd2db75 | J19: qvf-app
A20: Executive Dashboard | B20: ThousandSep | C20: , | E20: NaN | F20: No | G20: Yes | H20: qvapp_variablelist | I20: 747f56fa-948a-45a1-95f8-2b1f4551366c | J20: qvf-app
A21: Executive Dashboard | B21: DecimalSep | C21: . | E21: NaN | F21: No | G21: Yes | H21: qvapp_variablelist | I21: c85be7aa-6b92-4e86-bbb2-31d344d69267 | J21: qvf-app
A22: Executive Dashboard | B22: MoneyThousandSep | C22: , | E22: NaN | F22: No | G22: Yes | H22: qvapp_variablelist | I22: fd4da8fb-05ba-4cf9-af49-ab7a7a09cd21 | J22: qvf-app
A23: Executive Dashboard | B23: MoneyDecimalSep | C23: . | E23: NaN | F23: No | G23: Yes | H23: qvapp_variablelist | I23: 96ec746a-5f74-4243-86b7-28d9d0319184 | J23: qvf-app
A24: Executive Dashboard | B24: MoneyFormat | C24: $#,##0.00;($#,##0.00) | E24: NaN | F24: No | G24: Yes | H24: qvapp_variablelist | I24: e48d23bd-2e5b-4ec4-a204-36c8a8e88f98 | J24: qvf-app
A25: Executive Dashboard | B25: TimeFormat | C25: h:mm:ss TT | E25: NaN | F25: No | G25: Yes | H25: qvapp_variablelist | I25: 1d9dad3c-fd6d-4db3-a668-c77d5526c4c5 | J25: qvf-app
A26: Executive Dashboard | B26: DateFormat | C26: M/D/YYYY | E26: NaN | F26: No | G26: Yes | H26: qvapp_variablelist | I26: ac75b553-286a-4091-9aa6-ac9fef2d1202 | J26: qvf-app
A27: Executive Dashboard | B27: TimestampFormat | C27: M/D/YYYY h:mm:ss[.fff] TT | E27: NaN | F27: No | G27: Yes | H27: qvapp_variablelist | I27: 3cafd7e3-8a17-4a71-acdb-dc0a3bee4ee3 | J27: qvf-app
A28: Executive Dashboard | B28: MonthNames | C28: Jan;Feb;Mar;Apr;May;Jun;Jul;Aug;Sep;Oct;Nov;Dec | E28: NaN | F28: No | G28: Yes | H28: qvapp_variablelist | I28: d5467aca-f106-4b10-9ff0-6ac2327f8336 | J28: qvf-app
A29: Executive Dashboard | B29: DayNames | C29: Mon;Tue;Wed;Thu;Fri;Sat;Sun | E29: NaN | F29: No | G29: Yes | H29: qvapp_variablelist | I29: 70e078d5-9a3a-4a94-aa3c-d1753e4fa102 | J29: qvf-app
A30: Executive Dashboard | B30: vCurrentMonthNum | C30: 5 | E30: 5 | F30: No | G30: Yes | H30: qvapp_variablelist | I30: f8d38860-b6dc-4ba4-9bdb-3f026b24b459 | J30: qvf-app
A31: Executive Dashboard | B31: vCurrentMonth | C31: May | E31: 5 | F31: No | G31: Yes | H31: qvapp_variablelist | I31: b29854c2-53e2-47ad-8608-b987a1c55acf | J31: qvf-app
A32: Executive Dashboard | B32: vCurrentYear | C32: 2013 | E32: 2013 | F32: No | G32: Yes | H32: qvapp_variablelist | I32: 3e6785f5-f438-4f7b-b005-989de7a63a19 | J32: qvf-app
A33: Executive Dashboard | B33: vTodaysDate | C33: 41425 | E33: 41425 | F33: No | G33: Yes | H33: qvapp_variablelist | I33: 3f8db8c7-ceda-4958-93fe-ced25544a097 | J33: qvf-app
A34: Executive Dashboard | B34: v12month | C34: 41060 | E34: 41060 | F34: No | G34: Yes | H34: qvapp_variablelist | I34: fabd907b-6a19-4942-9e35-41c1804959ba | J34: qvf-app
A35: Executive Dashboard | B35: vRolling12months | C35: 41060 | E35: 41060 | F35: No | G35: Yes | H35: qvapp_variablelist | I35: 88fda23d-b35e-490e-b6ff-98171e3a7ea6 | J35: qvf-app
A36: Executive Dashboard | B36: vOldDate | C36: 41425 | E36: 41425 | F36: No | G36: Yes | H36: qvapp_variablelist | I36: cf8d6274-feb7-4200-a2fc-855f8ad20015 | J36: qvf-app
A37: Executive Dashboard | B37: vToday | C37: 5/31/2013 | E37: 41425 | F37: No | G37: Yes | H37: qvapp_variablelist | I37: 4f515b4b-09de-4c87-8e6f-13dffc627264 | J37: qvf-app
A38: Executive Dashboard | B38: vAdjDays | C38: 0 | E38: 0 | F38: No | G38: Yes | H38: qvapp_variablelist | I38: b86c7e8a-a66a-42f2-9b60-779b2324c337 | J38: qvf-app
A39: Executive Dashboard | B39: vVolume | C39: 0 | E39: 0 | F39: No | G39: Yes | H39: qvapp_variablelist | I39: eaf3c994-9fc5-4f8e-936d-283ee267c424 | J39: qvf-app
A40: Executive Dashboard | B40: vPrice | C40: 1 | E40: 1 | F40: No | G40: Yes | H40: qvapp_variablelist | I40: 64490398-338b-4c9a-8804-e4881fea735e | J40: qvf-app
A41: Executive Dashboard | B41: vCost | C41: -2 | E41: -2 | F41: No | G41: Yes | H41: qvapp_variablelist | I41: 8ae837ce-5c7c-41dc-9695-779d50787b44 | J41: qvf-app
A42: Executive Dashboard | B42: vShowChart | C42: 1 | E42: 1 | F42: No | G42: Yes | H42: qvapp_variablelist | I42: 1efc7ea9-a4e5-49c3-9eb4-5c6baeabf968 | J42: qvf-app
A43: Executive Dashboard | B43: vTargetSales | C43: =sum([Budget Amount]) | E43: NaN | F43: Yes | G43: Yes | H43: qvapp_variablelist | I43: 17718c1a-9592-424b-84dd-14b579e6cd1d | J43: qvf-app
A44: Executive Dashboard | B44: vTargetExpenses | C44: 10500000 | E44: 10500000 | F44: No | G44: Yes | H44: qvapp_variablelist | I44: 339610c8-e320-4cce-be61-2f451f9bcc67 | J44: qvf-app
A45: Executive Dashboard | B45: vSalesAnalysis | C45: 1 | E45: 1 | F45: No | G45: Yes | H45: qvapp_variablelist | I45: d320cea0-4373-45bb-adf3-ec4b84f52db8 | J45: qvf-app
A46: Executive Dashboard | B46: vYear | C46: =Concat(DISTINCT [Fiscal Year], ',') | E46: NaN | F46: Yes | G46: Yes | H46: qvapp_variablelist | I46: a31db449-aa13-4d72-84a4-154829565f66 | J46: qvf-app
A47: Executive Dashboard | B47: vTargetInventory | C47: 2000000 | E47: 2000000 | F47: No | G47: Yes | H47: qvapp_variablelist | I47: 0952c056-2bd4-4082-8eb3-100f32da1e4d | J47: qvf-app
A48: Executive Dashboard | B48: vQVDPath | C48: Database\QVD\ | E48: NaN | F48: No | G48: Yes | H48: qvapp_variablelist | I48: cca26043-3bd8-4b33-bfca-6b3d79165cae | J48: qvf-app
A49: Executive Dashboard | B49: HidePrefix | C49: _ | E49: NaN | F49: No | G49: Yes | H49: qvapp_variablelist | I49: fb42b1a6-ea72-4e40-8c3f-ed33eebb0fc6 | J49: qvf-app
A50: Executive Dashboard | B50: vLanguage | C50: =Minstring(_LANGUAGE) | E50: NaN | F50: Yes | G50: Yes | H50: qvapp_variablelist | I50: 0da70f9c-0116-4bca-8635-415a9249113f | J50: qvf-app
A51: Executive Dashboard | B51: vYTDYear | C51: =max([Fiscal Year]) | E51: NaN | F51: Yes | G51: Yes | H51: qvapp_variablelist | I51: 76d8b60b-2094-4ef4-9fb5-02bb4f686564 | J51: qvf-app
A52: Executive Dashboard | B52: vYTDMonth | C52: =if(GetSelectedCount(FiscalMonth) = 0, Month(max({<_HistoryFlag = {"1"}>} YYYYMM)), concat(distinct FiscalMonth, ',')) | E52: NaN | F52: Yes | G52: Yes | H52: qvapp_variablelist | I52: a7f9c033-31b5-4788-b964-396e7864f36e | J52: qvf-app
A53: Executive Dashboard | B53: FLOPPY | C53: D: | E53: NaN | F53: No | G53: Yes | H53: qvapp_variablelist | I53: ccd401c1-78db-41e5-8197-82d02b207cc9 | J53: qvf-app
A54: First Qlikview Report | B54: ErrorMode | E54: 1 | F54: No | G54: Yes | H54: qvapp_variablelist | I54: a129edb5-45a3-4d66-8d77-90b5f9206540 | J54: qvf-app
A55: First Qlikview Report | B55: StripComments | E55: 1 | F55: No | G55: Yes | H55: qvapp_variablelist | I55: 12cb96eb-1b74-4901-b940-caabc189e58c | J55: qvf-app
A56: First Qlikview Report | B56: OpenUrlTimeout | E56: 86400 | F56: No | G56: Yes | H56: qvapp_variablelist | I56: d0aadbb8-4683-44af-9724-19399b6792ae | J56: qvf-app
A57: First Qlikview Report | B57: ScriptError | E57: 0 | F57: No | G57: Yes | H57: qvapp_variablelist | I57: cd1f67b6-b5f2-4c55-beb8-818403a5f47a | J57: qvf-app
A58: First Qlikview Report | B58: ScriptErrorCount | C58: 0 | E58: 0 | F58: No | G58: Yes | H58: qvapp_variablelist | I58: 159be8ca-9d5d-4a4b-a137-427bef766c65 | J58: qvf-app
A59: First Qlikview Report | B59: ScriptErrorList | E59: NaN | F59: No | G59: Yes | H59: qvapp_variablelist | I59: b1492e54-1088-4c86-95ee-391be2c07087 | J59: qvf-app
A60: Helpdesk Management | B60: CD | C60: D: | E60: NaN | F60: No | G60: Yes | H60: qvapp_variablelist | I60: b8db01aa-3704-43e7-a903-4e7c6ec40bfd | J60: qvf-app
A61: Helpdesk Management | B61: QvPath | C61: C:\Users\cbo\AppData\Local\Programs\QlikView | E61: NaN | F61: No | G61: Yes | H61: qvapp_variablelist | I61: 29e6ed3a-609d-442f-9618-264a40607f44 | J61: qvf-app
A62: Helpdesk Management | B62: QvRoot | C62: C: | E62: NaN | F62: No | G62: Yes | H62: qvapp_variablelist | I62: b33881f3-3211-46bd-91da-fd63f3e4d238 | J62: qvf-app
A63: Helpdesk Management | B63: QvWorkPath | C63: C:/Users/cbo/Documents/Qlik/QlikView/Apps | E63: NaN | F63: No | G63: Yes | H63: qvapp_variablelist | I63: 33a83350-d428-4cad-a0f0-eee9878c31b2 | J63: qvf-app
A64: Helpdesk Management | B64: QvWorkRoot | C64: C: | E64: NaN | F64: No | G64: Yes | H64: qvapp_variablelist | I64: 20538bc3-ac79-4d61-b291-e953bec5b02e | J64: qvf-app
A65: Helpdesk Management | B65: WinPath | C65: C:\Windows | E65: NaN | F65: No | G65: Yes | H65: qvapp_variablelist | I65: 07398cc4-47c8-4328-ab6e-9928dc0befe2 | J65: qvf-app
A66: Helpdesk Management | B66: WinRoot | C66: C: | E66: NaN | F66: No | G66: Yes | H66: qvapp_variablelist | I66: aa98f25e-4cc7-4c87-82f7-88aae2ce4c46 | J66: qvf-app
A67: Helpdesk Management | B67: ErrorMode | E67: 1 | F67: No | G67: Yes | H67: qvapp_variablelist | I67: bef719a3-e211-483b-a541-72bcd97723e0 | J67: qvf-app
A68: Helpdesk Management | B68: StripComments | E68: 1 | F68: No | G68: Yes | H68: qvapp_variablelist | I68: 36b0ace6-ff8e-4552-82b2-9d2f66bbf405 | J68: qvf-app
A69: Helpdesk Management | B69: OpenUrlTimeout | E69: 86400 | F69: No | G69: Yes | H69: qvapp_variablelist | I69: 3e5a6675-def3-40e4-a577-e67a95b15a4a | J69: qvf-app
A70: Helpdesk Management | B70: ScriptErrorCount | C70: 0 | E70: 0 | F70: No | G70: Yes | H70: qvapp_variablelist | I70: 7ba8c398-4d88-4337-8d16-e49f9ed8df63 | J70: qvf-app
A71: Helpdesk Management | B71: ScriptErrorList | E71: NaN | F71: No | G71: Yes | H71: qvapp_variablelist | I71: 108c5a05-45e7-47c4-a17d-18d41f701b40 | J71: qvf-app
A72: Helpdesk Management | B72: ScriptError | E72: 0 | F72: No | G72: Yes | H72: qvapp_variablelist | I72: de2bd80a-d2f9-43c0-9081-9df38416b9df | J72: qvf-app
A73: Helpdesk Management | B73: ThousandSep | C73: , | E73: NaN | F73: No | G73: Yes | H73: qvapp_variablelist | I73: 787e3a58-8c79-4338-acba-958155ce600a | J73: qvf-app
A74: Helpdesk Management | B74: DecimalSep | C74: . | E74: NaN | F74: No | G74: Yes | H74: qvapp_variablelist | I74: 325e45f4-2d35-4e94-a1d9-863e2d53dfc2 | J74: qvf-app
A75: Helpdesk Management | B75: MoneyThousandSep | C75: , | E75: NaN | F75: No | G75: Yes | H75: qvapp_variablelist | I75: 8e7fad9b-3c0a-4749-8031-20b0c21fc0b7 | J75: qvf-app
A76: Helpdesk Management | B76: MoneyDecimalSep | C76: . | E76: NaN | F76: No | G76: Yes | H76: qvapp_variablelist | I76: 2f1615d8-344f-440d-8eec-41b78873f1f0 | J76: qvf-app
A77: Helpdesk Management | B77: MoneyFormat | C77: $#,##0.00;($#,##0.00) | E77: NaN | F77: No | G77: Yes | H77: qvapp_variablelist | I77: 37ab6a8a-91b0-4819-9785-8eb49cdd342e | J77: qvf-app
A78: Helpdesk Management | B78: TimeFormat | C78: h:mm:ss TT | E78: NaN | F78: No | G78: Yes | H78: qvapp_variablelist | I78: 4acaacad-79fa-417b-98d5-32fde29bcc39 | J78: qvf-app
A79: Helpdesk Management | B79: DateFormat | C79: M/D/YYYY | E79: NaN | F79: No | G79: Yes | H79: qvapp_variablelist | I79: 05acd155-070a-41a0-ac92-ad9e9b93c770 | J79: qvf-app
A80: Helpdesk Management | B80: TimestampFormat | C80: M/D/YYYY h:mm:ss[.fff] TT | E80: NaN | F80: No | G80: Yes | H80: qvapp_variablelist | I80: d0f1bc63-3647-4e80-8939-7d5e55594957 | J80: qvf-app
A81: Helpdesk Management | B81: MonthNames | C81: Jan;Feb;Mar;Apr;May;Jun;Jul;Aug;Sep;Oct;Nov;Dec | E81: NaN | F81: No | G81: Yes | H81: qvapp_variablelist | I81: 472d4e74-4cf2-4a18-ab0f-46d9d3d14fda | J81: qvf-app
A82: Helpdesk Management | B82: DayNames | C82: Mon;Tue;Wed;Thu;Fri;Sat;Sun | E82: NaN | F82: No | G82: Yes | H82: qvapp_variablelist | I82: 8f6e91ec-ad5b-42a4-abd0-56d17143b385 | J82: qvf-app
A83: Helpdesk Management | B83: vRunningDate | C83: =maxstring([Running Date]) | E83: NaN | F83: Yes | G83: Yes | H83: qvapp_variablelist | I83: fc2d4c98-65e3-4f76-b7c6-9e27ac96ce07 | J83: qvf-app
A84: Helpdesk Management | B84: vToday | C84: 41084 | E84: 41084 | F84: No | G84: Yes | H84: qvapp_variablelist | I84: 862f6372-fcb5-479a-a404-45bc98db259f | J84: qvf-app
A85: Helpdesk Management | B85: vLanguage | C85: =Minstring(#LANGUAGE) | E85: NaN | F85: Yes | G85: Yes | H85: qvapp_variablelist | I85: 54a7625c-91f3-4e02-a11f-d7fbd8088ac2 | J85: qvf-app
A86: Helpdesk Management | B86: vinfo_on | C86: 0 | E86: 0 | F86: No | G86: Yes | H86: qvapp_variablelist | I86: d1ac53a4-b9fe-469d-8043-288d08c7c606 | J86: qvf-app
A87: Helpdesk Management | B87: HidePrefix | C87: # | E87: NaN | F87: No | G87: Yes | H87: qvapp_variablelist | I87: 4a458ad7-7a03-4645-a387-83d787abd506 | J87: qvf-app
A88: Helpdesk Management | B88: FLOPPY | C88: D: | E88: NaN | F88: No | G88: Yes | H88: qvapp_variablelist | I88: 4d8194ce-bf9c-45ae-b13a-79bddfa86f9d | J88: qvf-app
A89: Sales Analysis | B89: ErrorMode | E89: 1 | F89: No | G89: Yes | H89: qvapp_variablelist | I89: e57c6cd6-9920-4468-a9da-968a4599006a | J89: qvf-app
A90: Sales Analysis | B90: StripComments | E90: 1 | F90: No | G90: Yes | H90: qvapp_variablelist | I90: bc13615f-69a2-4c70-b2e0-d0660beee210 | J90: qvf-app
A91: Sales Analysis | B91: OpenUrlTimeout | E91: 86400 | F91: No | G91: Yes | H91: qvapp_variablelist | I91: 1022022a-54cf-4066-9684-dcf82f988518 | J91: qvf-app
A92: Sales Analysis | B92: ScriptErrorCount | C92: 0 | E92: 0 | F92: No | G92: Yes | H92: qvapp_variablelist | I92: fb44eae3-cada-4ce2-af6c-13469514e901 | J92: qvf-app
A93: Sales Analysis | B93: ScriptErrorList | E93: NaN | F93: No | G93: Yes | H93: qvapp_variablelist | I93: 0aae63b1-24f2-45f8-8342-c79ee29a55e5 | J93: qvf-app
A94: Sales Analysis | B94: ScriptError | E94: 0 | F94: No | G94: Yes | H94: qvapp_variablelist | I94: f19cfb23-7ecf-4087-b100-a2efb56a5367 | J94: qvf-app
A95: Sales Analysis | B95: ThousandSep | C95: . | E95: NaN | F95: No | G95: Yes | H95: qvapp_variablelist | I95: e5a327ad-476d-42af-9049-1e6b7519c6d0 | J95: qvf-app
A96: Sales Analysis | B96: DecimalSep | C96: , | E96: NaN | F96: No | G96: Yes | H96: qvapp_variablelist | I96: b6461f03-5834-4149-ad63-b9f69c1a3eaa | J96: qvf-app
A97: Sales Analysis | B97: MoneyThousandSep | C97: . | E97: NaN | F97: No | G97: Yes | H97: qvapp_variablelist | I97: 240a190e-379d-486b-82f2-0d76c282156b | J97: qvf-app
A98: Sales Analysis | B98: MoneyDecimalSep | C98: , | E98: NaN | F98: No | G98: Yes | H98: qvapp_variablelist | I98: f5f538b5-3ff8-4113-b412-a310d34e3a52 | J98: qvf-app
A99: Sales Analysis | B99: MoneyFormat | C99: € #.##0,00;-€ #.##0,00 | E99: NaN | F99: No | G99: Yes | H99: qvapp_variablelist | I99: 6f751fd5-b363-40ab-bf12-12d2aa531264 | J99: qvf-app
A100: Sales Analysis | B100: TimeFormat | C100: hh:mm:ss | E100: NaN | F100: No | G100: Yes | H100: qvapp_variablelist | I100: 5d5ce757-e9e9-4851-aebb-e554cda0af84 | J100: qvf-app
A101: Sales Analysis | B101: DateFormat | C101: DD/MM/YYYY | E101: NaN | F101: No | G101: Yes | H101: qvapp_variablelist | I101: ee71eed5-5488-484b-946e-9f9163ef9041 | J101: qvf-app
A102: Sales Analysis | B102: TimestampFormat | C102: DD/MM/YYYY hh:mm:ss[.fff] | E102: NaN | F102: No | G102: Yes | H102: qvapp_variablelist | I102: 15492f82-d1b8-408b-80c8-4e1276c1365b | J102: qvf-app
A103: Sales Analysis | B103: MonthNames | C103: gen;feb;mar;apr;mag;giu;lug;ago;set;ott;nov;dic | E103: NaN | F103: No | G103: Yes | H103: qvapp_variablelist | I103: f8a99760-717f-4fc3-8f3a-79b24ed4bb2a | J103: qvf-app
...

Sheet Bookmarks
C2: Bookmarks · saved selections
A5: =HYPERLINK("#'Discovery'!A1","« Back to Discovery") | B5: Saved selections with title, description and stored selection text.
A6: App | B6: ID | C6: Title | D6: Description | E6: Created | F6: Stored strings (selections)
A7: Executive Dashboard | B7: SmDXrz | F7: JsonProperty | sheetId | "FaQeFa" | JsonProperty> | selectionFields | "Product Sub Group Desc, Sales Rep Name" | JsonProperty | creationDate | "2014-08-14" | qInfo | SmDXrz | bookmark | qMetaDef | JsonProperty/ | title | "Sales Analysis - Low Margin Sales" | JsonProperty | description | Product Sub Group Desc | Wine | Preserves | Sugar | Coffee | Cheese | Deli Meats | Hot Dogs | Bologna | Fresh Vegetables | Fresh Fruit | Sales Rep Name | Amalia Craig | Brenda Kegler | Cart Lynch | Cary Frank | Deborah Halmon | Dennis Fisher | Judy Rowlett | Cheryle Sincock | Don Simmons | Jimmie Holley
A8: Executive Dashboard | B8: gG01 | F8: JsonProperty* | title | "Sales vs Margin by Sales Rep" | JsonProperty | description | JsonProperty | sheetId | "FaQeFa" | JsonProperty | creationDate | "2014-02-13" | JsonObject | qMeta | JsonObject | qSelectionInfo | HyperCube | qHyperCube | JsonProperty | title | "Sales Rep Name" | JsonProperty | autoSort | true | JsonProperty | cId | "qvHTMd" | JsonProperty | othersLabel | "Others" | Sales Rep Name | Sales Rep Name | $ascii | $text | JsonProperty | autoSort | true | JsonProperty | cId | "RPfsxLb" | Margin %
A9: Executive Dashboard | B9: QTzpe | F9: JsonProperty# | title | "Average Sales Per Day" | JsonProperty | description | JsonProperty | sheetId | "FaQeFa" | JsonProperty | creationDate | "2014-02-13" | JsonObject | qMeta | JsonObject | qSelectionInfo | HyperCube | qHyperCube | JsonProperty | title | "Year Month" | JsonProperty | autoSort | true | JsonProperty | cId | "EtdNTQp" | JsonProperty | othersLabel | "Others" Year Month | Year Month | $key | $numeric | $integer $timestamp | $date | JsonProperty | autoSort | true | JsonProperty | cId | "SwcJjj"
A10: Executive Dashboard | B10: PqgqBSe | F10: JsonProperty: | title | "Total Revenue by Product Group = $18,226,161" | JsonProperty | description | JsonProperty | sheetId | "FaQeFa" | JsonProperty | creationDate | "2014-02-13" | JsonObject | qMeta | JsonObject | qSelectionInfo | HyperCube | qHyperCube | JsonProperty$ | title | "Product Sub Group Desc" | JsonProperty | autoSort | true | JsonProperty | cId | "HBLVQ" | JsonProperty | othersLabel | "Others" | Product Sub Group Desc | Product Sub Group Desc | $ascii | $text | JsonProperty | autoSort | true | JsonProperty | cId | "GCkjvhs" | Revenue
A11: Executive Dashboard | B11: EQ01 | F11: JsonProperty" | title | "Revenue by Sales Rep" | JsonProperty | description | JsonProperty | sheetId | "JsCeVm" | JsonProperty | creationDate | "2014-02-13" | JsonObject | qMeta | JsonObject | qSelectionInfo | HyperCube | qHyperCube | JsonProperty | title | "Segment" | JsonProperty | autoSort | true | JsonProperty | cId | "pZXhfv" | JsonProperty | othersLabel | "Others" | Segment | Segment | $ascii | $text | JsonProperty | title | "Sales Rep Name" | JsonProperty | autoSort | true | JsonProperty
A12: Executive Dashboard | B12: maUepV | F12: JsonProperty1 | title | "Avg Sales Per Day vs AR Avg Balance" | JsonProperty | description | JsonProperty | sheetId | "JsCeVm" | JsonProperty | creationDate | "2014-02-13" | JsonObject | qMeta | JsonObject | qSelectionInfo | HyperCube | qHyperCube | JsonProperty | title | "Customer" | JsonProperty | autoSort | true | JsonProperty | cId | "PQLbzwV" | JsonProperty | othersLabel | "Others" | Customer" | Customer | $text | JsonProperty | autoSort | true | JsonProperty | cId | "apJF" | AR Average Balance | JsonProperty
A13: Executive Dashboard | B13: MpPJDAW | F13: JsonProperty* | title | "Sales vs Margin by Sales Rep" | JsonProperty | description | JsonProperty | sheetId | "FaQeFa" | JsonProperty | creationDate | "2014-02-13" | JsonObject | qMeta | JsonObject | qSelectionInfo | HyperCube | qHyperCube | JsonProperty | title | "Sales Rep Name" | JsonProperty | autoSort | true | JsonProperty | cId | "qvHTMd" | JsonProperty | othersLabel | "Others" | Sales Rep Name | Sales Rep Name | $ascii | $text | JsonProperty | autoSort | true | JsonProperty | cId | "RPfsxLb" | Margin %
A14: Executive Dashboard | B14: VpUAq | F14: JsonProperty | title | JsonProperty | description | JsonProperty | sheetId | "JsCeVm" | JsonProperty | creationDate | "2014-02-13" | JsonObject | qMeta | JsonObject | qSelectionInfo | HyperCube | qHyperCube | JsonProperty | autoSort | true | JsonProperty | cId | "jjyuUY" | Days Sales Outstanding | #,##0 | ,@Tb~ | @Tb~ | 82@Tb~ | 82@Tb~ | 82@Tb~ | JsonObject( | refLine | JsonArray | refLines | JsonProperty | showTitles | true | JsonProperty | subtitle | JsonProperty | footnote
A15: Executive Dashboard | B15: Vp01 | F15: JsonProperty | title | JsonProperty | description | JsonProperty | sheetId | "JsCeVm" | JsonProperty | creationDate | "2014-02-13" | JsonObject | qMeta | JsonObject | qSelectionInfo | HyperCube | qHyperCube | JsonProperty | autoSort | true | JsonProperty | cId | "jjyuUY" | Days Sales Outstanding | #,##0 | ,@Tb~ | @Tb~ | 82@Tb~ | 82@Tb~ | 82@Tb~ | JsonObject( | refLine | JsonArray | refLines | JsonProperty | showTitles | true | JsonProperty | subtitle | JsonProperty | footnote
A16: Executive Dashboard | B16: ML01 | F16: JsonProperty* | title | "Sales vs Margin by Sales Rep" | JsonProperty | description | JsonProperty | sheetId | "FaQeFa" | JsonProperty | creationDate | "2014-02-13" | JsonObject | qMeta | JsonObject | qSelectionInfo | HyperCube | qHyperCube | JsonProperty | title | "Sales Rep Name" | JsonProperty | autoSort | true | JsonProperty | cId | "qvHTMd" | JsonProperty | othersLabel | "Others" | Sales Rep Name | Sales Rep Name | $ascii | $text | JsonProperty | autoSort | true | JsonProperty | cId | "RPfsxLb" | Margin %
A17: Executive Dashboard | B17: TaukZtb | F17: JsonProperty: | title | "Total Revenue by Product Group = $23,251,083" | JsonProperty | description | JsonProperty | sheetId | "FaQeFa" | JsonProperty | creationDate | "2014-02-13" | JsonObject | qMeta | JsonObject | qSelectionInfo | HyperCube | qHyperCube | JsonProperty$ | title | "Product Sub Group Desc" | JsonProperty | autoSort | true | JsonProperty | cId | "HBLVQ" | JsonProperty | othersLabel | "Others" | Product Sub Group Desc | Product Sub Group Desc | $ascii | $text | JsonProperty | autoSort | true | JsonProperty | cId | "GCkjvhs" | Revenue
A18: Executive Dashboard | B18: uFjMpUZ | F18: JsonProperty | sheetId | "FaQeFa" | JsonProperty> | selectionFields | "Product Sub Group Desc, Sales Rep Name" | JsonProperty | creationDate | "2014-08-14" | qInfo | uFjMpUZ | bookmark | qMetaDef | JsonProperty0 | title | "Sales Analysis - High Margin Sales" | JsonProperty | description | Product Sub Group Desc | Wine | Preserves | Sugar | Coffee | Cheese | Deli Meats | Hot Dogs | Bologna | Fresh Vegetables | Fresh Fruit | Sales Rep Name | Amanda Honda | Amelia Fields | Brenda Gibson | Craig Lary | David Howard | David Laychak | John Greg | Edward Laychak | John Davis | Janice Scott
... A32: Executive Dashboard | B32: jPTmcR | F32: JsonProperty# | title | "Amount Overdue vs DOS" | JsonProperty | description | JsonProperty | sheetId | "JsCeVm" | JsonProperty | creationDate | "2014-02-13" | JsonObject | qMeta | JsonObject | qSelectionInfo | HyperCube | qHyperCube | JsonProperty | title | "Customer" | JsonProperty | autoSort | true | JsonProperty | cId | "PQLbzwV" | JsonProperty | othersLabel | "Others" | Customer" | Customer | $text | JsonProperty | autoSort | true | JsonProperty | cId | "BaYBW" | Days Sales Outstanding | @g]
A33: First Qlikview Report | B33: Document\BM01 | E33: 2026-09-24T14:02:04.643Z | F33: Document\BM01 | $LASTKNOWNSTATE@ | Document\SH01
A34: First Qlikview Report | B34: Document\BM02 | E34: 2026-09-24T14:02:04.643Z | F34: Document\BM02 | $LASTKNOWNSTATE@ | Region_Key | R04 | Document\SH01 | Document\CS01 | Document\SO01 | Document\LB01 | Document\CH01 | Document\CS01 | Document\SO01 | Document\LB01 | Document\CH01 | Order_ID | Order_ID | Sum(Quantity) | Order_ID
A35: Helpdesk Management | B35: TnmRpt | F35: JsonProperty& | title | "Open Cases Request Types" | JsonProperty | description | JsonProperty | sheetId | "hPVwh" | JsonProperty | creationDate | "2014-02-19" | JsonObject | qMeta | JsonObject | qSelectionInfo | HyperCube | qHyperCube | JsonProperty | autoSort | true | JsonProperty | cId | "gfexXV" | JsonProperty | othersLabel | "Others" | Case Record Type | Case Record Type | $ascii | $text | JsonProperty | autoSort | true | JsonProperty | cId | "SsFUES" Open Cases | 255@o | 255@o | General IT Support~7 | 193@h
A36: Helpdesk Management | B36: a8e13766-33a3-404e-869e-e220aec58991 | F36: JsonProperty& | title | "Open Cases Request Types" | JsonProperty | description | JsonProperty | sheetId | "hPVwh" | JsonProperty | creationDate | "2014-08-22" | JsonObject | qSelectionInfo | HyperCube | qHyperCube | JsonProperty | autoSort | true | JsonProperty | cId | "gfexXV" | JsonProperty | othersLabel | "Others" | Case Record Type | Case Record Type | $ascii | $text | Case Record Type | JsonProperty | autoSort | true | JsonProperty | cId | "SsFUES" Open Cases | ###0 | 214@j | General IT Support~7 | 120@^ | Hardware Request~7
A37: Helpdesk Management | B37: VjQtmv | F37: JsonProperty. | title | "Case Distribution by IT Resource" | JsonProperty | description | JsonProperty | sheetId | "kHgmg" | JsonProperty | creationDate | "2014-08-22" | JsonObject | qSelectionInfo | HyperCube | qHyperCube | JsonProperty | autoSort | true | JsonProperty | cId | "gHJPJm" | JsonProperty | othersLabel | "Others" | Case Owner Group | Case Owner Group | $ascii | $text | Case Owner Group | JsonProperty | autoSort | true | JsonProperty | cId | "UJXjLJ" | JsonProperty | othersLabel | "Others" Case Owner | Case Owner | $ascii
A38: Helpdesk Management | B38: fmPtU | F38: JsonProperty | title | "Resource Details" | JsonProperty | description | JsonProperty | sheetId | "kHgmg" | JsonProperty | creationDate | "2014-08-27" | JsonObject | qSelectionInfo | HyperCube | qHyperCube | JsonArray | columnOrder | JsonProperty | JsonProperty | JsonProperty | JsonProperty | JsonProperty | JsonProperty | JsonProperty | JsonProperty | JsonProperty | JsonProperty | JsonProperty | autoSort | false | JsonProperty | cId | "CMRptr" | JsonProperty | othersLabel | "Others" Case Owner | Case Owner | $ascii | $text | Case Owner
A39: Helpdesk Management | B39: gsUbn | F39: JsonProperty | title | "Cases by Priority" | JsonProperty | description | JsonProperty | sheetId | "hPVwh" | JsonProperty | creationDate | "2014-02-19" | JsonObject | qMeta | JsonObject | qSelectionInfo | HyperCube | qHyperCube | JsonProperty | autoSort | false | JsonProperty | cId | "hScCFZ" | JsonProperty | othersLabel | "Others" | Priority | Priority | $ascii | $text | JsonProperty | autoSort | true | JsonProperty | cId | "PdXjFW" Open Cases | 193@h | 193@h | High~7 | 26@:
A40: Helpdesk Management | B40: Ew01 | F40: JsonProperty" | title | "Case Details: 5Cases" | JsonProperty | description | JsonProperty | sheetId | "VkcYvCR" | JsonProperty | creationDate | "2014-02-19" | JsonObject | qMeta | JsonObject | qSelectionInfo | HyperCube | qHyperCube | JsonProperty | autoSort | true | JsonProperty | cId | "WCDwys" | JsonProperty | othersLabel | "Others" CaseNumber | CaseNumber | $ascii | $text | JsonProperty | autoSort | true | JsonProperty | cId | "fnWKM" | JsonProperty | othersLabel | "Others" | Subject | Subject
A41: Helpdesk Management | B41: SENvLWT | F41: JsonProperty | title | "Cases by Priority" | JsonProperty | description | JsonProperty | sheetId | "hPVwh" | JsonProperty | creationDate | "2014-08-22" | JsonObject | qSelectionInfo | HyperCube | qHyperCube | JsonProperty | autoSort | false | JsonProperty | cId | "hScCFZ" | JsonProperty | othersLabel | "Others" | Priority | Priority | $ascii | $text | Priority | JsonProperty | autoSort | true | JsonProperty | cId | "PdXjFW" Open Cases | ###0 | 214@j | High~7 | 72@R | Medium~7
A42: Helpdesk Management | B42: FrnmUQs | F42: JsonProperty | title | "Open Cases by Age" | JsonProperty | description | JsonProperty | sheetId | "pKnjHKZ" | JsonProperty | creationDate | "2014-02-19" | JsonObject | qMeta | JsonObject | qSelectionInfo | HyperCube | qHyperCube | JsonProperty | autoSort | false | JsonProperty | cId | "VxpnqUy" | JsonProperty | othersLabel | "Others" | Case Timetable | Case Timetable | $ascii | $text | JsonProperty | autoSort | true | JsonProperty | cId | "JzRvRJJ" Open Cases | 75@R | 75@R | Yesterday~7 | 2-7 days~7
A43: Helpdesk Management | B43: unGmT | F43: JsonProperty | title | "Open Cases by Age" | JsonProperty | description | JsonProperty | sheetId | "pKnjHKZ" | JsonProperty | creationDate | "2014-02-19" | JsonObject | qMeta | JsonObject | qSelectionInfo | HyperCube | qHyperCube | JsonProperty | autoSort | false | JsonProperty | cId | "VxpnqUy" | JsonProperty | othersLabel | "Others" | Case Timetable | Case Timetable | $ascii | $text | JsonProperty | autoSort | true | JsonProperty | cId | "JzRvRJJ" Open Cases | 417@z | 417@z | Yesterday~7 | 30@>
A44: Helpdesk Management | B44: chgQYX | F44: JsonProperty | title | "Resource Details" | JsonProperty | description | JsonProperty | sheetId | "kHgmg" | JsonProperty | creationDate | "2014-08-22" | JsonObject | qSelectionInfo | HyperCube | qHyperCube | JsonArray | columnOrder | JsonProperty | JsonProperty | JsonProperty | JsonProperty | JsonProperty | JsonProperty | JsonProperty | JsonProperty | JsonProperty | JsonProperty | JsonProperty | autoSort | false | JsonProperty | cId | "CMRptr" | JsonProperty | othersLabel | "Others" Case Owner | Case Owner | $ascii | $text | Case Owner
A45: Helpdesk Management | B45: 4df984f9-1150-4383-9347-ce1993287a34 | F45: JsonProperty | title | "Open Cases by Age" | JsonProperty | description | JsonProperty | sheetId | "pKnjHKZ" | JsonProperty | creationDate | "2014-08-22" | JsonObject | qSelectionInfo | HyperCube | qHyperCube | JsonProperty | autoSort | false | JsonProperty | cId | "VxpnqUy" | JsonProperty | othersLabel | "Others" | Case Timetable | Case Timetable | $ascii | $text | Case Timetable | JsonProperty | autoSort | true | JsonProperty | cId | "JzRvRJJ" Open Cases | ###0 | 75@R | Yesterday~7 | 2-7 days~7 | 20@4
A46: Helpdesk Management | B46: 63cd685c-aa73-4821-a0a0-271b2b4494c7 | F46: JsonProperty | title | "Open Cases by Age" | JsonProperty | description | JsonProperty | sheetId | "kHgmg" | JsonProperty | creationDate | "2014-08-27" | JsonObject | qSelectionInfo | HyperCube | qHyperCube | JsonProperty | autoSort | true | JsonProperty | cId | "ZPMVHbm" | JsonProperty | othersLabel | "Others" | Case Timetable | Case Timetable | $ascii | $text | Case Timetable | JsonProperty | autoSort | true | JsonProperty | cId | "SdSNjp" Open Cases | ###0 | JsonProperty | type | "colorByExpression" | 61@N
... A106: Tutorial creazione nuova app | B106: BKPXpFb | F106: JsonProperty | sheetId | "pNfY" | JsonProperty | selectionFields | "Year" | JsonProperty- | creationDate | "2016-01-31T20:13:09.663Z" | qInfo | BKPXpFb | bookmark | qMetaDef | JsonProperty) | title | "Dashboard - Year (\"2013\")" | JsonProperty | description | Year

Sheet Stories
C2: Stories · data storytelling
A5: =HYPERLINK("#'Discovery'!A1","« Back to Discovery") | B5: Stories with slide and slide-item counts.
A6: App | B6: ID | C6: Title | D6: Description | E6: Slides | F6: Slide items
A7: Executive Dashboard | B7: Cbpvks | C7: Margin Analysis by Sales Rep | D7: This story provides an analysis of sales reps with low margin and sales reps with high margin sales and the top product sold in each group. | E7: 4 | F7: 20
A8: Helpdesk Management | B8: VPqmKgS | C8: Analyzing High and Medium Priority Cases | D8: High and Medium priority cases attract the most attention within our company. These cases need to be resolved quickly. There are times when cases remain open beyond our preset resolution time. We need to quickly identify those cases and figure out what resources are necessary to resolve the cases. | E8: 4 | F8: 13
A9: Tutorial creazione nuova app | B9: CjNwb | C9: Three largest regions | E9: 7 | F9: 21

Sheet LoadScript
D2: Load script · one row per script tab
A5: =HYPERLINK("#'Discovery'!A1","« Back to Discovery") | B5: One row per script tab: lines and counts of LOAD, SELECT, STORE, JOIN and other statements.
A6: App | B6: # | C6: Tab | D6: Lines | E6: LOAD | F6: SQL SELECT | G6: STORE | H6: DROP | I6: JOIN | J6: CONCATENATE | K6: MAPPING | L6: CROSSTABLE | M6: INTERVALMATCH | N6: SUB | O6: FOR/DO loops | P6: SET/LET | Q6: INLINE tables
A7: Executive Dashboard | B7: 1 | C7: Main | D7: 38 | E7: 1 | F7: 0 | G7: 0 | H7: 0 | I7: 0 | J7: 0 | K7: 0 | L7: 0 | M7: 0 | N7: 0 | O7: 0 | P7: 20 | Q7: 0
A8: Executive Dashboard | B8: 2 | C8: Account | D8: 18 | E8: 3 | F8: 0 | G8: 0 | H8: 0 | I8: 0 | J8: 0 | K8: 0 | L8: 0 | M8: 0 | N8: 0 | O8: 0 | P8: 0 | Q8: 0
A9: Executive Dashboard | B9: 3 | C9: Budget | D9: 9 | E9: 1 | F9: 0 | G9: 0 | H9: 0 | I9: 0 | J9: 0 | K9: 0 | L9: 0 | M9: 0 | N9: 0 | O9: 0 | P9: 0 | Q9: 0
A10: Executive Dashboard | B10: 4 | C10: Inventory | D10: 8 | E10: 1 | F10: 0 | G10: 0 | H10: 0 | I10: 0 | J10: 0 | K10: 0 | L10: 0 | M10: 0 | N10: 0 | O10: 0 | P10: 0 | Q10: 0
A11: Executive Dashboard | B11: 5 | C11: Product | D11: 29 | E11: 5 | F11: 0 | G11: 0 | H11: 0 | I11: 0 | J11: 0 | K11: 0 | L11: 0 | M11: 0 | N11: 0 | O11: 0 | P11: 0 | Q11: 0
A12: Executive Dashboard | B12: 6 | C12: Sales Rep | D12: 5 | E12: 1 | F12: 0 | G12: 0 | H12: 0 | I12: 0 | J12: 0 | K12: 0 | L12: 0 | M12: 0 | N12: 0 | O12: 0 | P12: 0 | Q12: 0
A13: Executive Dashboard | B13: 7 | C13: FactTable | D13: 62 | E13: 5 | F13: 0 | G13: 0 | H13: 1 | I13: 0 | J13: 1 | K13: 0 | L13: 0 | M13: 0 | N13: 0 | O13: 0 | P13: 0 | Q13: 0
A14: Executive Dashboard | B14: 8 | C14: Customer | D14: 34 | E14: 4 | F14: 0 | G14: 0 | H14: 0 | I14: 0 | J14: 0 | K14: 0 | L14: 0 | M14: 0 | N14: 0 | O14: 0 | P14: 0 | Q14: 0
A15: Executive Dashboard | B15: 9 | C15: Calendar | D15: 10 | E15: 1 | F15: 0 | G15: 0 | H15: 0 | I15: 0 | J15: 0 | K15: 0 | L15: 0 | M15: 0 | N15: 0 | O15: 0 | P15: 0 | Q15: 0
A16: Executive Dashboard | B16: 10 | C16: AR | D16: 20 | E16: 2 | F16: 0 | G16: 0 | H16: 0 | I16: 0 | J16: 0 | K16: 0 | L16: 0 | M16: 0 | N16: 0 | O16: 0 | P16: 0 | Q16: 0
A17: First Qlikview Report | B17: 1 | C17: Main | D17: 13 | E17: 1 | F17: 0 | G17: 0 | H17: 0 | I17: 0 | J17: 0 | K17: 0 | L17: 0 | M17: 0 | N17: 0 | O17: 0 | P17: 0 | Q17: 0
A18: Helpdesk Management | B18: 1 | C18: Main | D18: 14 | E18: 0 | F18: 0 | G18: 0 | H18: 0 | I18: 0 | J18: 0 | K18: 0 | L18: 0 | M18: 0 | N18: 0 | O18: 0 | P18: 11 | Q18: 0
... A30: Tutorial creazione script | B30: 2 | C30: Dati | D30: 33 | E30: 4 | F30: 0 | G30: 0 | H30: 0 | I30: 0 | J30: 0 | K30: 0 | L30: 0 | M30: 0 | N30: 0 | O30: 0 | P30: 0 | Q30: 0

Sheet DataSources
C2: Data sources · what the load scripts read and write
A5: =HYPERLINK("#'Discovery'!A1","« Back to Discovery") | B5: Every connection, SQL query, file, resident and inline load and STORE in every script.
A6: App | B6: Tab | C6: Source type | D6: Source / target | E6: Loaded into table | F6: Distinct in app | G6: Distinct in portfolio
A7: Executive Dashboard | B7: Main | C7: QVD file | D7: lib://Executive Dashboard Data/AccountGroupMaster.qvd | F7: =IF(AND(C7<>"Resident table",C7<>"STORE output",COUNTIFS(A$7:A7,A7,D$7:D7,D7)=1),1,0) | G7: =IF(AND(C7<>"Resident table",C7<>"STORE output",COUNTIF(D$7:D7,D7)=1),1,0)
A8: Executive Dashboard | B8: Account | C8: QVD file | D8: lib://Executive Dashboard Data/AccountGroupMaster.qvd | E8: AccountGroupMaster | F8: =IF(AND(C8<>"Resident table",C8<>"STORE output",COUNTIFS(A$7:A8,A8,D$7:D8,D8)=1),1,0) | G8: =IF(AND(C8<>"Resident table",C8<>"STORE output",COUNTIF(D$7:D8,D8)=1),1,0)
A9: Executive Dashboard | B9: Account | C9: QVD file | D9: lib://Executive Dashboard Data/AccountGroupMaster.qvd | F9: =IF(AND(C9<>"Resident table",C9<>"STORE output",COUNTIFS(A$7:A9,A9,D$7:D9,D9)=1),1,0) | G9: =IF(AND(C9<>"Resident table",C9<>"STORE output",COUNTIF(D$7:D9,D9)=1),1,0)
A10: Executive Dashboard | B10: Account | C10: QVD file | D10: lib://Executive Dashboard Data/AccountMaster.qvd | E10: AccountMaster | F10: =IF(AND(C10<>"Resident table",C10<>"STORE output",COUNTIFS(A$7:A10,A10,D$7:D10,D10)=1),1,0) | G10: =IF(AND(C10<>"Resident table",C10<>"STORE output",COUNTIF(D$7:D10,D10)=1),1,0)
A11: Executive Dashboard | B11: Budget | C11: Excel file | D11: lib://Executive Dashboard Data/RegionalSales.xlsx | E11: Budget | F11: =IF(AND(C11<>"Resident table",C11<>"STORE output",COUNTIFS(A$7:A11,A11,D$7:D11,D11)=1),1,0) | G11: =IF(AND(C11<>"Resident table",C11<>"STORE output",COUNTIF(D$7:D11,D11)=1),1,0)
A12: Executive Dashboard | B12: Inventory | C12: QVD file | D12: lib://Executive Dashboard Data/InventoryBalances.qvd | E12: InventoryBalances | F12: =IF(AND(C12<>"Resident table",C12<>"STORE output",COUNTIFS(A$7:A12,A12,D$7:D12,D12)=1),1,0) | G12: =IF(AND(C12<>"Resident table",C12<>"STORE output",COUNTIF(D$7:D12,D12)=1),1,0)
A13: Executive Dashboard | B13: Product | C13: QVD file | D13: lib://Executive Dashboard Data/ItemMaster.qvd | E13: ItemMaster | F13: =IF(AND(C13<>"Resident table",C13<>"STORE output",COUNTIFS(A$7:A13,A13,D$7:D13,D13)=1),1,0) | G13: =IF(AND(C13<>"Resident table",C13<>"STORE output",COUNTIF(D$7:D13,D13)=1),1,0)
A14: Executive Dashboard | B14: Product | C14: QVD file | D14: lib://Executive Dashboard Data/ProductSubGroupMaster.qvd | E14: ProductSubGroupMaster | F14: =IF(AND(C14<>"Resident table",C14<>"STORE output",COUNTIFS(A$7:A14,A14,D$7:D14,D14)=1),1,0) | G14: =IF(AND(C14<>"Resident table",C14<>"STORE output",COUNTIF(D$7:D14,D14)=1),1,0)
A15: Executive Dashboard | B15: Product | C15: QVD file | D15: lib://Executive Dashboard Data/ProductTypeMaster.qvd | E15: ProductTypeMaster | F15: =IF(AND(C15<>"Resident table",C15<>"STORE output",COUNTIFS(A$7:A15,A15,D$7:D15,D15)=1),1,0) | G15: =IF(AND(C15<>"Resident table",C15<>"STORE output",COUNTIF(D$7:D15,D15)=1),1,0)
A16: Executive Dashboard | B16: Product | C16: QVD file | D16: lib://Executive Dashboard Data/ProductGroupMaster.qvd | E16: ProductGroupMaster | F16: =IF(AND(C16<>"Resident table",C16<>"STORE output",COUNTIFS(A$7:A16,A16,D$7:D16,D16)=1),1,0) | G16: =IF(AND(C16<>"Resident table",C16<>"STORE output",COUNTIF(D$7:D16,D16)=1),1,0)
A17: Executive Dashboard | B17: Product | C17: QVD file | D17: lib://Executive Dashboard Data/ItemBranchMaster.qvd | E17: ItemBranchMaster | F17: =IF(AND(C17<>"Resident table",C17<>"STORE output",COUNTIFS(A$7:A17,A17,D$7:D17,D17)=1),1,0) | G17: =IF(AND(C17<>"Resident table",C17<>"STORE output",COUNTIF(D$7:D17,D17)=1),1,0)
A18: Executive Dashboard | B18: Sales Rep | C18: QVD file | D18: lib://Executive Dashboard Data/SalesRepMaster.qvd | E18: SalesRepMaster | F18: =IF(AND(C18<>"Resident table",C18<>"STORE output",COUNTIFS(A$7:A18,A18,D$7:D18,D18)=1),1,0) | G18: =IF(AND(C18<>"Resident table",C18<>"STORE output",COUNTIF(D$7:D18,D18)=1),1,0)
A19: Executive Dashboard | B19: FactTable | C19: QVD file | D19: lib://Executive Dashboard Data/FactTable.qvd | E19: FactTable | F19: =IF(AND(C19<>"Resident table",C19<>"STORE output",COUNTIFS(A$7:A19,A19,D$7:D19,D19)=1),1,0) | G19: =IF(AND(C19<>"Resident table",C19<>"STORE output",COUNTIF(D$7:D19,D19)=1),1,0)
A20: Executive Dashboard | B20: FactTable | C20: Excel file | D20: lib://Executive Dashboard Data/Expenses.xls | E20: Expenses | F20: =IF(AND(C20<>"Resident table",C20<>"STORE output",COUNTIFS(A$7:A20,A20,D$7:D20,D20)=1),1,0) | G20: =IF(AND(C20<>"Resident table",C20<>"STORE output",COUNTIF(D$7:D20,D20)=1),1,0)
A21: Executive Dashboard | B21: FactTable | C21: Resident table | D21: Expenses | F21: =IF(AND(C21<>"Resident table",C21<>"STORE output",COUNTIFS(A$7:A21,A21,D$7:D21,D21)=1),1,0) | G21: =IF(AND(C21<>"Resident table",C21<>"STORE output",COUNTIF(D$7:D21,D21)=1),1,0)
A22: Executive Dashboard | B22: FactTable | C22: Resident table | D22: FactTable | E22: HistoryFlag | F22: =IF(AND(C22<>"Resident table",C22<>"STORE output",COUNTIFS(A$7:A22,A22,D$7:D22,D22)=1),1,0) | G22: =IF(AND(C22<>"Resident table",C22<>"STORE output",COUNTIF(D$7:D22,D22)=1),1,0)
A23: Executive Dashboard | B23: FactTable | C23: Excel file | D23: lib://Executive Dashboard Data/ExpenseAccounts.xls | E23: Accounts | F23: =IF(AND(C23<>"Resident table",C23<>"STORE output",COUNTIFS(A$7:A23,A23,D$7:D23,D23)=1),1,0) | G23: =IF(AND(C23<>"Resident table",C23<>"STORE output",COUNTIF(D$7:D23,D23)=1),1,0)
A24: Executive Dashboard | B24: Customer | C24: QVD file | D24: lib://Executive Dashboard Data/CustomerAddressMaster.qvd | E24: CustomerAddressMaster | F24: =IF(AND(C24<>"Resident table",C24<>"STORE output",COUNTIFS(A$7:A24,A24,D$7:D24,D24)=1),1,0) | G24: =IF(AND(C24<>"Resident table",C24<>"STORE output",COUNTIF(D$7:D24,D24)=1),1,0)
A25: Executive Dashboard | B25: Customer | C25: QVD file | D25: lib://Executive Dashboard Data/CustomerMap.qvd | E25: CustomerMap | F25: =IF(AND(C25<>"Resident table",C25<>"STORE output",COUNTIFS(A$7:A25,A25,D$7:D25,D25)=1),1,0) | G25: =IF(AND(C25<>"Resident table",C25<>"STORE output",COUNTIF(D$7:D25,D25)=1),1,0)
A26: Executive Dashboard | B26: Customer | C26: QVD file | D26: lib://Executive Dashboard Data/CustomerMaster.qvd | E26: CustomerMaster | F26: =IF(AND(C26<>"Resident table",C26<>"STORE output",COUNTIFS(A$7:A26,A26,D$7:D26,D26)=1),1,0) | G26: =IF(AND(C26<>"Resident table",C26<>"STORE output",COUNTIF(D$7:D26,D26)=1),1,0)
A27: Executive Dashboard | B27: Customer | C27: QVD file | D27: lib://Executive Dashboard Data/ChannelMaster.qvd | E27: ChannelMaster | F27: =IF(AND(C27<>"Resident table",C27<>"STORE output",COUNTIFS(A$7:A27,A27,D$7:D27,D27)=1),1,0) | G27: =IF(AND(C27<>"Resident table",C27<>"STORE output",COUNTIF(D$7:D27,D27)=1),1,0)
A28: Executive Dashboard | B28: Calendar | C28: QVD file | D28: lib://Executive Dashboard Data/Calendar.qvd | E28: Calendar | F28: =IF(AND(C28<>"Resident table",C28<>"STORE output",COUNTIFS(A$7:A28,A28,D$7:D28,D28)=1),1,0) | G28: =IF(AND(C28<>"Resident table",C28<>"STORE output",COUNTIF(D$7:D28,D28)=1),1,0)
A29: Executive Dashboard | B29: AR | C29: QVD file | D29: lib://Executive Dashboard Data/ARSummary.qvd | E29: ARSummary | F29: =IF(AND(C29<>"Resident table",C29<>"STORE output",COUNTIFS(A$7:A29,A29,D$7:D29,D29)=1),1,0) | G29: =IF(AND(C29<>"Resident table",C29<>"STORE output",COUNTIF(D$7:D29,D29)=1),1,0)
A30: Executive Dashboard | B30: AR | C30: QVD file | D30: lib://Executive Dashboard Data/ARSummary-1.qvd | E30: ARSummary-1 | F30: =IF(AND(C30<>"Resident table",C30<>"STORE output",COUNTIFS(A$7:A30,A30,D$7:D30,D30)=1),1,0) | G30: =IF(AND(C30<>"Resident table",C30<>"STORE output",COUNTIF(D$7:D30,D30)=1),1,0)
A31: First Qlikview Report | B31: Main | C31: Excel file | D31: C:\Users\1815\Downloads\Sales_Data.xlsx | F31: =IF(AND(C31<>"Resident table",C31<>"STORE output",COUNTIFS(A$7:A31,A31,D$7:D31,D31)=1),1,0) | G31: =IF(AND(C31<>"Resident table",C31<>"STORE output",COUNTIF(D$7:D31,D31)=1),1,0)
A32: Helpdesk Management | B32: Cases | C32: QVD file | D32: Database\Helpdesk Cases.qvd | E32: Helpdesk Cases | F32: =IF(AND(C32<>"Resident table",C32<>"STORE output",COUNTIFS(A$7:A32,A32,D$7:D32,D32)=1),1,0) | G32: =IF(AND(C32<>"Resident table",C32<>"STORE output",COUNTIF(D$7:D32,D32)=1),1,0)
A33: Helpdesk Management | B33: Cases | C33: QVD file | D33: Database\Requests.qvd | E33: Requests | F33: =IF(AND(C33<>"Resident table",C33<>"STORE output",COUNTIFS(A$7:A33,A33,D$7:D33,D33)=1),1,0) | G33: =IF(AND(C33<>"Resident table",C33<>"STORE output",COUNTIF(D$7:D33,D33)=1),1,0)
A34: Helpdesk Management | B34: Cases | C34: QVD file | D34: Database\Calendar.qvd | E34: Calendar | F34: =IF(AND(C34<>"Resident table",C34<>"STORE output",COUNTIFS(A$7:A34,A34,D$7:D34,D34)=1),1,0) | G34: =IF(AND(C34<>"Resident table",C34<>"STORE output",COUNTIF(D$7:D34,D34)=1),1,0)
A35: Sales Analysis | B35: Sezione generata automaticamente | C35: Excel file | D35: lib://simple_data/Customers and Categories.xlsx | E35: Categories | F35: =IF(AND(C35<>"Resident table",C35<>"STORE output",COUNTIFS(A$7:A35,A35,D$7:D35,D35)=1),1,0) | G35: =IF(AND(C35<>"Resident table",C35<>"STORE output",COUNTIF(D$7:D35,D35)=1),1,0)
A36: Sales Analysis | B36: Sezione generata automaticamente | C36: Excel file | D36: lib://simple_data/Customers and Categories.xlsx | E36: Customers | F36: =IF(AND(C36<>"Resident table",C36<>"STORE output",COUNTIFS(A$7:A36,A36,D$7:D36,D36)=1),1,0) | G36: =IF(AND(C36<>"Resident table",C36<>"STORE output",COUNTIF(D$7:D36,D36)=1),1,0)
A37: Sales Analysis | B37: Sezione generata automaticamente | C37: Excel file | D37: lib://simple_data/Customers and Categories.xlsx | E37: Products | F37: =IF(AND(C37<>"Resident table",C37<>"STORE output",COUNTIFS(A$7:A37,A37,D$7:D37,D37)=1),1,0) | G37: =IF(AND(C37<>"Resident table",C37<>"STORE output",COUNTIF(D$7:D37,D37)=1),1,0)
A38: Sales Analysis | B38: Sezione generata automaticamente | C38: Excel file | D38: lib://simple_data/Orders.xls | E38: Orders$ | F38: =IF(AND(C38<>"Resident table",C38<>"STORE output",COUNTIFS(A$7:A38,A38,D$7:D38,D38)=1),1,0) | G38: =IF(AND(C38<>"Resident table",C38<>"STORE output",COUNTIF(D$7:D38,D38)=1),1,0)
A39: TryConfigColorAndAgrField | B39: Load data | C39: Inline table | D39: INLINE | E39: Data | F39: =IF(AND(C39<>"Resident table",C39<>"STORE output",COUNTIFS(A$7:A39,A39,D$7:D39,D39)=1),1,0) | G39: =IF(AND(C39<>"Resident table",C39<>"STORE output",COUNTIF(D$7:D39,D39)=1),1,0)
A40: TryConfigColorAndAgrField | B40: Load data | C40: Inline table | D40: INLINE | E40: TipiPrezzo | F40: =IF(AND(C40<>"Resident table",C40<>"STORE output",COUNTIFS(A$7:A40,A40,D$7:D40,D40)=1),1,0) | G40: =IF(AND(C40<>"Resident table",C40<>"STORE output",COUNTIF(D$7:D40,D40)=1),1,0)
A41: TryExtensions | B41: Initial data | C41: Inline table | D41: INLINE | F41: =IF(AND(C41<>"Resident table",C41<>"STORE output",COUNTIFS(A$7:A41,A41,D$7:D41,D41)=1),1,0) | G41: =IF(AND(C41<>"Resident table",C41<>"STORE output",COUNTIF(D$7:D41,D41)=1),1,0)
A42: Tutorial creazione nuova app | B42: Sezione generata automaticamente | C42: Excel file | D42: lib://Tutorial source/Sales.xlsx | E42: Sales | F42: =IF(AND(C42<>"Resident table",C42<>"STORE output",COUNTIFS(A$7:A42,A42,D$7:D42,D42)=1),1,0) | G42: =IF(AND(C42<>"Resident table",C42<>"STORE output",COUNTIF(D$7:D42,D42)=1),1,0)
A43: Tutorial creazione nuova app | B43: Sezione generata automaticamente | C43: Excel file | D43: lib://Tutorial source/Item master.xlsx | E43: Item master | F43: =IF(AND(C43<>"Resident table",C43<>"STORE output",COUNTIFS(A$7:A43,A43,D$7:D43,D43)=1),1,0) | G43: =IF(AND(C43<>"Resident table",C43<>"STORE output",COUNTIF(D$7:D43,D43)=1),1,0)
A44: Tutorial creazione nuova app | B44: Sezione generata automaticamente | C44: Excel file | D44: lib://Tutorial source/Cities.xlsx | E44: Cities | F44: =IF(AND(C44<>"Resident table",C44<>"STORE output",COUNTIFS(A$7:A44,A44,D$7:D44,D44)=1),1,0) | G44: =IF(AND(C44<>"Resident table",C44<>"STORE output",COUNTIF(D$7:D44,D44)=1),1,0)
A45: Tutorial creazione nuova app | B45: Sezione generata automaticamente | C45: Text / CSV file | D45: lib://Tutorial source/Sales rep.csv | E45: Sales rep | F45: =IF(AND(C45<>"Resident table",C45<>"STORE output",COUNTIFS(A$7:A45,A45,D$7:D45,D45)=1),1,0) | G45: =IF(AND(C45<>"Resident table",C45<>"STORE output",COUNTIF(D$7:D45,D45)=1),1,0)
A46: Tutorial creazione nuova app | B46: Sezione generata automaticamente | C46: Excel file | D46: lib://Tutorial source/Customers.xlsx | E46: Customer | F46: =IF(AND(C46<>"Resident table",C46<>"STORE output",COUNTIFS(A$7:A46,A46,D$7:D46,D46)=1),1,0) | G46: =IF(AND(C46<>"Resident table",C46<>"STORE output",COUNTIF(D$7:D46,D46)=1),1,0)
A47: Tutorial creazione nuova app | B47: Master calendar | C47: Resident table | D47: TempCalendar | E47: MasterCalendar | F47: =IF(AND(C47<>"Resident table",C47<>"STORE output",COUNTIFS(A$7:A47,A47,D$7:D47,D47)=1),1,0) | G47: =IF(AND(C47<>"Resident table",C47<>"STORE output",COUNTIF(D$7:D47,D47)=1),1,0)

Sheet DataTables
C2: Data tables · tables stored in the apps
A5: =HYPERLINK("#'Discovery'!A1","« Back to Discovery") | B5: Tables stored in each app with source, row and column counts (none when saved without data).
A6: App | B6: Table | C6: Source | D6: Rows | E6: Columns | F6: Field names
A7: Executive Dashboard | B7: AccountGroupMaster | C7: C:\Users\cbo\Documents\Qlik\QlikView\Apps\Executive Dashboard Files\AccountGroupMaster.qvd | D7: 27 | E7: 2 | F7: AccountGroup, AccountGroupDesc
A8: Executive Dashboard | B8: AccountMaster | C8: C:\Users\cbo\Documents\Qlik\QlikView\Apps\Executive Dashboard Files\AccountMaster.qvd | D8: 103 | E8: 2 | F8: Account, AccountGroup
A9: Executive Dashboard | B9: Budget | C9: C:\Users\cbo\Documents\Qlik\QlikView\Apps\Executive Dashboard Files\RegionalSales.xlsx | D9: 216 | E9: 2 | F9: MonthlyRegionKey, Budget Amount
A10: Executive Dashboard | B10: InventoryBalances | C10: C:\Users\cbo\Documents\Qlik\QlikView\Apps\Executive Dashboard Files\InventoryBalances.qvd | D10: 836 | E10: 5 | F10: Line Desc 1, ClassTurns, ThroughputQty, CostPrice, StockOH
A11: Executive Dashboard | B11: ItemMaster | C11: C:\Users\cbo\Documents\Qlik\QlikView\Apps\Executive Dashboard Files\ItemMaster.qvd | D11: 826 | E11: 5 | F11: Product Group, Product Line, Product Sub Group, Product Type, Short Name
A12: Executive Dashboard | B12: ProductSubGroupMaster | C12: C:\Users\cbo\Documents\Qlik\QlikView\Apps\Executive Dashboard Files\ProductSubGroupMaster.qvd | D12: 70 | E12: 2 | F12: Product Sub Group, Product Sub Group Desc
A13: Executive Dashboard | B13: ProductTypeMaster | C13: C:\Users\cbo\Documents\Qlik\QlikView\Apps\Executive Dashboard Files\ProductTypeMaster.qvd | D13: 31 | E13: 2 | F13: Product Type, Product Type Desc
A14: Executive Dashboard | B14: ProductGroupMaster | C14: C:\Users\cbo\Documents\Qlik\QlikView\Apps\Executive Dashboard Files\ProductGroupMaster.qvd | D14: 17 | E14: 2 | F14: Product Group, Product Group Desc
A15: Executive Dashboard | B15: ItemBranchMaster | C15: C:\Users\cbo\Documents\Qlik\QlikView\Apps\Executive Dashboard Files\ItemBranchMaster.qvd | D15: 906 | E15: 2 | F15: Item-Branch Key, Short Name
A16: Executive Dashboard | B16: SalesRepMaster | C16: C:\Users\cbo\Documents\Qlik\QlikView\Apps\Executive Dashboard Files\SalesRepMaster.qvd | D16: 64 | E16: 2 | F16: Sales Rep, Sales Rep Name
A17: Executive Dashboard | B17: FactTable | C17: C:\Users\cbo\Documents\Qlik\QlikView\Apps\Executive Dashboard Files\Expenses.xls | D17: 73417 | E17: 22 | F17: MonthlyRegionKey, Region, Address Number, CustKey, Invoice Number, Item-Branch Key, Late Shipment, Line Desc 1, Open Order Amount, Order Number, Order Status, OrderDate, OrderID, OrderStat, Promised Delivery Date, Sales Amount, Sales Cost Amount, Sales Margin Amount, Sales Price, Sales Quantity, Ship To, YYYYMM
A18: Executive Dashboard | B18: Expenses | C18: C:\Users\cbo\Documents\Qlik\QlikView\Apps\Executive Dashboard Files\Expenses.xls | D18: 7447 | E18: 4 | F18: MonthlyRegionKey, Account, ExpenseActual, ExpenseBudget
... A50: Tutorial creazione script | B50: Transactions | C50: AUTOGENERATE(1000) | D50: 1999 | E50: 9 | F50: TransLineID, TransID, Num, Dim1, Dim2, Dim3, Expression1, Expression2, Expression3

Sheet Fields
C2: Fields · the data models
A5: =HYPERLINK("#'Discovery'!A1","« Back to Discovery") | B5: Data-model fields with distinct values, tables, tags and sample values.
A6: App | B6: Field | C6: Distinct values | D6: In tables | E6: Tags | F6: Number format | G6: Sample values
A7: Executive Dashboard | B7: AccountGroup | C7: 23 | D7: AccountGroupMaster, AccountMaster | G7: 61999, 69999, 71999, 74999, 75999, 11999, 12999, 15999
A8: Executive Dashboard | B8: AccountGroupDesc | C8: 3 | D8: AccountGroupMaster | G8: Staff Costs, General Costs, Other Costs
A9: Executive Dashboard | B9: Account | C9: 103 | D9: AccountMaster, Expenses, Accounts | G9: 61099, 61199, 61299, 61399, 61499, 61599, 61699, 62099
A10: Executive Dashboard | B10: MonthlyRegionKey | C10: 252 | D10: Budget, FactTable, Expenses | G10: Africa_201101, Africa_201102, Africa_201103, Africa_201104, Africa_201105, Africa_201106, Africa_201107, Africa_201108
A11: Executive Dashboard | B11: Budget Amount | C11: 185 | D11: Budget | G11: 67900, 65100, 51000, 20600, 16200, 55000, 62900, 72800
A12: Executive Dashboard | B12: Line Desc 1 | C12: 824 | D12: InventoryBalances, FactTable | G12: Ebony Sweet Peas, High Top Fresh Lima Beans, Bravo Fancy Canned Oysters, Gorilla 1% Milk, Nationeel Corn Chips, Nationeel Raisins, Washington Diet Cola, Best Choice Frosted Donuts
A13: Executive Dashboard | B13: ClassTurns | C13: 22 | D13: InventoryBalances | G13: 48 <= Turns < 51, 9 <= Turns < 12, 0 <= Turns < 3, 6 <= Turns < 9, 3 <= Turns < 6, 15 <= Turns < 18, 30 <= Turns < 33, 21 <= Turns < 24
A14: Executive Dashboard | B14: ThroughputQty | C14: 457 | D14: InventoryBalances | G14: 6480, 547, 142, 468, 1547, 276, 10539, 816
A15: Executive Dashboard | B15: CostPrice | C15: 711 | D15: InventoryBalances | G15: 62.36, 9.98, 26.71, 41.65, 16.11, 19.76, 2, 12.97
A16: Executive Dashboard | B16: StockOH | C16: 263 | D16: InventoryBalances | G16: 129.5, 54.5, 71, 58.5, 773.5, 69, 5269.5, 51
A17: Executive Dashboard | B17: Product Group | C17: 17 | D17: ItemMaster, ProductGroupMaster | G17: 1, 2, 3, 4, 5, 6, 7, 10
A18: Executive Dashboard | B18: Product Line | C18: 2 | D18: ItemMaster | G18: 2, 1
... A38: Executive Dashboard | B38: OrderStat | C38: 4 | D38: FactTable | G38: Open, Invoiced, Cancelled, Back Order
A39: Executive Dashboard | B39: Promised Delivery Date | C39: 0 | D39: FactTable
A40: Executive Dashboard | B40: Sales Amount | C40: 14561 | D40: FactTable | G40: 6.3500000000000005, 0, 35.410000000000004, 61.980000000000004, 151.43, 101.54, 129.79, -40.660000000000004
A41: Executive Dashboard | B41: Sales Cost Amount | C41: 7846 | D41: FactTable | G41: 0, 16.830000000000002, 22.28, 105.18, 65.73, 85.35000000000001, 166.94, 66.28
A42: Executive Dashboard | B42: Sales Margin Amount | C42: 15879 | D42: FactTable | G42: 6.35, 0, 18.58, 39.7, 46.25, 35.81, 44.44, -40.66
A43: Executive Dashboard | B43: Sales Price | C43: 7695 | D43: FactTable | F43: $#,##0.00;($#,##0.00) | G43: 6.3500000000000005, 0, 35.410000000000004, 20.66, 75.71000000000001, 101.54, 129.78, 40.660000000000004
A44: Executive Dashboard | B44: Sales Quantity | C44: 306 | D44: FactTable | G44: 1, 3, 2, -1, 5, 10, -15, 12
A45: Executive Dashboard | B45: Ship To | C45: 429 | D45: FactTable | G45: 101032, 10000000, 10000455, 10000458, 101205, 101196, 101684, 100867
A46: Executive Dashboard | B46: YYYYMM | C46: 36 | D46: FactTable, HistoryFlag, Calendar | G46: 41518, 41579, 41609, 41548, 41487, 40634, 40940, 41030
A47: Executive Dashboard | B47: ExpenseActual | C47: 5013 | D47: Expenses | F47: ###0 | G47: 2170.86, 1894.73, 2218.04, 1976.48, 2076.7200000000003, 2109.51, 2042.79, 2210.64
A48: Executive Dashboard | B48: ExpenseBudget | C48: 2816 | D48: Expenses | F48: ###0 | G48: 2180.1, 2202.53, 2203.67, 2297.92, 2298.64, 2299.1, 2300.51, 2301.67
A49: Executive Dashboard | B49: _HistoryFlag | C49: 2 | D49: HistoryFlag | G49: 0, 1
A50: Executive Dashboard | B50: AccountDesc | C50: 45 | D50: Accounts | G50: Salaries and Wages, Overtime, Staff Temporary, Bonus, Reps Commission, Salary On Costs, Staff Benefits, Local Advertising
A51: Executive Dashboard | B51: Customer Address 1 | C51: 120 | D51: CustomerAddressMaster | G51: 4747 N Channel Ave, 167 East Kalamazoo Avenue, Worldwide Purchasing, RR1 Box 9, 3248 Auburn Boulevard, 6025 Corridor Parkway, 8901 Montana Avenue, PO Box 762
A52: Executive Dashboard | B52: Zip Code | C52: 116 | D52: CustomerAddressMaster | G52: 97208-3591, 49007, 48083, 56744, 95821, 78154-3214, 79925, 90630
A53: Executive Dashboard | B53: CustKeyAR | C53: 73 | D53: CustomerMap, ARSummary, ARSummary-1 | G53: 99985, 28, 64693, 55, 462, 96900, 42, 93333
A54: Executive Dashboard | B54: Business Family | C54: 6 | D54: CustomerMaster | G54: R2, R3, R1, O2, O1, R4
A55: Executive Dashboard | B55: Segment | C55: 8 | D55: CustomerMaster, ChannelMaster | G55: C1, C7, C6, C4, C2, C3, C8, C9
A56: Executive Dashboard | B56: Customer | C56: 130 | D56: CustomerMaster | G56: Ben and Jerry’s, Deak-Perera Group., Fill It, Fins, Hetrick Systems, Homebound, Idyllwild, J. S. Lee Associates
A57: Executive Dashboard | B57: Customer Number | C57: 130 | D57: CustomerMaster | G57: 10004245, 10009676, 10012226, 10012425, 10015793, 10016588, 10017314, 10017828
A58: Executive Dashboard | B58: Customer Type | C58: 2 | D58: CustomerMaster | G58: G2, G3
A59: Executive Dashboard | B59: Distribution Channel Mgr | C59: 5 | D59: CustomerMaster | G59: TT, JL, JV, OE, DB
A60: Executive Dashboard | B60: Division | C60: 2 | D60: CustomerMaster | G60: 2, 1
... A67: Executive Dashboard | B67: Fiscal Quarter | C67: 4 | D67: Calendar | G67: 1, 2, 3, 4
A68: Executive Dashboard | B68: Fiscal Year | C68: 3 | D68: Calendar | F68: ###0 | G68: 2011, 2012, 2013
A69: Executive Dashboard | B69: FiscalMonth | C69: 12 | D69: Calendar | G69: Jan, Feb, Mar, Apr, May, Jun, Jul, Aug
A70: Executive Dashboard | B70: FiscalMonthNum | C70: 12 | D70: Calendar | G70: 1, 2, 3, 4, 5, 6, 7, 8
A71: Executive Dashboard | B71: FiscalRollQt | C71: 12 | D71: Calendar | G71: 2010-1, 2011-1, 2012-1, 2010-2, 2011-2, 2012-2, 2010-3, 2011-3
A72: Executive Dashboard | B72: ARGross | C72: 73 | D72: ARSummary | G72: 5270.1359999999995, 3076.7416, 0, 7646.4436000000005, 264.14259999999996, 276798.64440000005, 675984.0798000001, 3732.775
A73: Executive Dashboard | B73: AROpen | C73: 60 | D73: ARSummary | G73: -30.872, 0, -113.9204, 24421.254800000002, 16622.5456, 1415.3418000000001, 1490.2098, 10766.1646
A74: Executive Dashboard | B74: ARCurrent | C74: 45 | D74: ARSummary | G74: 0, 26927.588600000003, 1242.02, 1152.3824, 3511.9586000000004, 8367.553, 18041.3758, 5557.0144
A75: Executive Dashboard | B75: AR1-30 | C75: 40 | D75: ARSummary | G75: 0, -2506.3338000000003, 188.3056, 262.9594, 521.0432000000001, 1240.7348, -2996.1616000000004, -251.2974
A76: Executive Dashboard | B76: AR31-60 | C76: 21 | D76: ARSummary | G76: -30.872, 0, 15192.220000000001, -2325.7734, 4253.298, 283.4988, 4017.1034000000004, -102.25840000000001
A77: Executive Dashboard | B77: AR60+ | C77: 29 | D77: ARSummary | G77: 0, -113.9204, -217.01860000000002, 1157.8768, 627.5006000000001, -13.0866, 4706.2664, -136
A78: Executive Dashboard | B78: ARCredit | C78: 29 | D78: ARSummary | G78: 2550, 16999.66, 5439.66, 17000, 51000, 680, 8500, 3059.66
A79: Executive Dashboard | B79: ARSalesPerDay | C79: 69 | D79: ARSummary | G79: -23.3546, 15.7386, 0.41140000000000004, 46.814600000000006, 1.3872, 1057.8284, 1335.6016, 12.512
A80: Executive Dashboard | B80: ARAvgBal | C80: 70 | D80: ARSummary | G80: 5064.1946, 943.755, 0, 1292.9384, 132.0696, 27149.7582, 32213.436, 545.751
... A82: Executive Dashboard | B82: ARAgeBal | C82: 132 | D82: ARSummary-1 | G82: 0, 26927.588600000003, 1242.02, 1152.3824, 3511.9586000000004, 8367.553, 18041.3758, 5557.0144
A83: First Qlikview Report | B83: Order_ID | C83: 100 | D83: Fact_Sales | E83: $numeric, $integer | G83: 1001, 1002, 1003, 1004, 1005, 1006, 1007, 1008
A84: First Qlikview Report | B84: Date_Key | C84: 12 | D84: Fact_Sales | E84: $numeric, $integer | G84: 20260201, 20260301, 20260401, 20260501, 20260601, 20260701, 20260801, 20260901
A85: First Qlikview Report | B85: Product_Key | C85: 5 | D85: Fact_Sales | E85: $ascii, $text | G85: P002, P003, P004, P005, P001
A86: First Qlikview Report | B86: Region_Key | C86: 4 | D86: Fact_Sales | E86: $ascii, $text | G86: R02, R03, R04, R01
A87: First Qlikview Report | B87: SalesRep_Key | C87: 5 | D87: Fact_Sales | E87: $ascii, $text | G87: S02, S03, S04, S05, S01
A88: First Qlikview Report | B88: Quantity | C88: 10 | D88: Fact_Sales | E88: $numeric, $integer | G88: 2, 3, 4, 5, 6, 7, 8, 9
A89: First Qlikview Report | B89: Unit_Cost | C89: 5 | D89: Fact_Sales | E89: $numeric, $integer | G89: 125, 150, 175, 200, 100
A90: First Qlikview Report | B90: Unit_Price | C90: 5 | D90: Fact_Sales | E90: $numeric | G90: 168.75, 202.5, 236.25, 270, 135
A91: First Qlikview Report | B91: Revenue | C91: 10 | D91: Fact_Sales | E91: $numeric | G91: 337.5, 607.5, 945, 1350, 810, 1181.25, 1620, 2126.25
A92: First Qlikview Report | B92: Profit | C92: 10 | D92: Fact_Sales | E92: $numeric | G92: 87.5, 157.5, 245, 350, 210, 306.25, 420, 551.25
A93: Helpdesk Management | B93: %CaseId | C93: 9031 | D93: Helpdesk Cases | G93: ABC112233445567050, ABC112233445567059, ABC112233445567068, ABC112233445567077, ABC112233445567086, ABC112233445567095, ABC112233445567104, ABC112233445567113
A94: Helpdesk Management | B94: Case_Date_Key | C94: 9031 | D94: Helpdesk Cases, Requests | G94: ABC112233445567050_12/9/2011, ABC112233445567059_12/9/2011, ABC112233445567068_12/6/2011, ABC112233445567077_12/6/2011, ABC112233445567086_12/9/2011, ABC112233445567095_12/6/2011, ABC112233445567104_12/10/2011, ABC112233445567113_12/10/2011
A95: Helpdesk Management | B95: Case Count | C95: 1 | D95: Helpdesk Cases | G95: 1
A96: Helpdesk Management | B96: CaseNumber | C96: 9031 | D96: Helpdesk Cases | G96: 00042775, 00042806, 00042400, 00042412, 00042843, 00042450, 00042920, 00042938
A97: Helpdesk Management | B97: Status | C97: 11 | D97: Helpdesk Cases | G97: Closed, On Hold, New, Pending Approval, Pending Customer Reply, In Process, Duplicate Case, Escalated
A98: Helpdesk Management | B98: Priority | C98: 3 | D98: Helpdesk Cases | G98: Low, High, Medium
A99: Helpdesk Management | B99: Priority Rank | C99: 6 | D99: Helpdesk Cases | G99: 5, 2, 3, 4, 1, 6
A100: Helpdesk Management | B100: Priority Sort | C100: 3 | D100: Helpdesk Cases | G100: 3, 1, 2
A101: Helpdesk Management | B101: Case Is Closed | C101: 2 | D101: Helpdesk Cases | G101: True, False
A102: Helpdesk Management | B102: Case Aging | C102: 396 | D102: Helpdesk Cases | G102: 101 07:09, 98 10:41, 93 09:21, 65 11:03, 65 04:25, 29 03:35, 36 02:41, 34 09:49
A103: Helpdesk Management | B103: Cases Open/Closed | C103: 2 | D103: Helpdesk Cases | G103: Closed Cases, Open Cases
A104: Helpdesk Management | B104: Case Closed Date | C104: 7979 | D104: Helpdesk Cases | G104: 12/21/2011, 12/21/2011, 12/7/2011, 12/21/2011, 12/15/2011, 12/23/2011, 12/24/2011, 12/10/2011
... A121: Helpdesk Management | B121: Month | C121: 12 | D121: Calendar | G121: Jun, May, Apr, Mar, Feb, Jan, Dec, Nov
A122: Helpdesk Management | B122: Year | C122: 3 | D122: Calendar | F122: ###0 | G122: 2012, 2011, 2010
A123: Helpdesk Management | B123: Quarter | C123: 4 | D123: Calendar | G123: Q2, Q1, Q4, Q3
A124: Helpdesk Management | B124: Number of New Cases | C124: 76 | D124: Calendar | F124: ###0 | G124: 233, 260, 316, 232, 259, 287, 246, 177
A125: Helpdesk Management | B125: Number of Closed Cases | C125: 69 | D125: Calendar | F125: ###0 | G125: 198, 219, 290, 221, 287, 241, 223, 267
A126: Sales Analysis | B126: CategoryID | C126: 8 | D126: Categories, Products | G126: 1, 2, 3, 4, 5, 6, 7, 8
A127: Sales Analysis | B127: CategoryName | C127: 8 | D127: Categories | G127: Men´s Clothes, Womens wear, Sportwear, Bath Clothes, Ladies´Footwear, Men´s Footwear, Children´s wear, Babywear
A128: Sales Analysis | B128: Description | C128: 8 | D128: Categories | G128: Fashion for Men, Fashion for Women, Sports…, Beachwear, Ladies Shoes, Men Shoes, 3-15 Years, 0-3 Years
A129: Sales Analysis | B129: Address | C129: 92 | D129: Customers | G129: 1 rue Alsace-Lorraine, 2, rue du Commerce, 5ª Ave. Los Palos Grandes, 8 Johnstown Road, 12 Brewery, 12 Orchestra Terrace, 12, rue des Bouchers, 23 Tsawassen Blvd.
A130: Sales Analysis | B130: City | C130: 70 | D130: Customers | G130: Toulouse, Lyon, Caracas, Cork, London, Walla Walla, Marseille, Tsawassen
A131: Sales Analysis | B131: ContactName | C131: 92 | D131: Customers | G131: Louise Davu, Pierre Robert, Antonio Palmer Amer, Robert Bolero, Ian Wright, Klaus Tarantino, Bernard de Gaule, James Hendersson
A132: Sales Analysis | B132: Country | C132: 21 | D132: Customers | G132: France, Venezuela, Ireland, United Kingdom, United States, Canada, Germany, Sweden
A133: Sales Analysis | B133: Customer | C133: 92 | D133: Customers | G133: Design, Art et Fashion, El Abrigo Mortal, Boleros, The sharped dressed man, For The Dark Night, La Legion Mercenaire, Big Foot Shoes
A134: Sales Analysis | B134: CustomerID | C134: 92 | D134: Customers, Orders$ | G134: 41, 84, 33, 37, 16, 43, 9, 10
A135: Sales Analysis | B135: Fax | C135: 68 | D135: Customers | G135: 61.77.61.11, 78.32.54.87, (2) 283-3397, NULL, (171) 555-9199, (509) 555-6221, 91.24.45.41, (604) 555-3745
A136: Sales Analysis | B136: Phone | C136: 90 | D136: Customers | G136: 61.77.61.10, 78.32.54.86, (2) 283-2951, NULL, (171) 555-2282, (509) 555-7969, 91.24.45.40, (604) 555-4729
A137: Sales Analysis | B137: PostalCode | C137: 63 | D137: Customers | G137: 31000, 69004, 1081, 12580, NULL, 99362, 13008, 67000
... A152: Sales Analysis | B152: Freight | C152: 783 | D152: Orders$ | G152: 43.48, 29.2, 79.16999999999999, 43.41, 23.2, 66.54, 49.18, 43.89
A153: Sales Analysis | B153: F13 | C153: 0 | D153: Orders$
A154: TryConfigColorAndAgrField | B154: NomeProdotto | C154: 3 | D154: Data | G154: Prodotto1, Prodotto2, Prodotto3
A155: TryConfigColorAndAgrField | B155: PrezzoAcquisto | C155: 3 | D155: Data | G155: 100, 200, 300
A156: TryConfigColorAndAgrField | B156: PrezzoRivendita | C156: 3 | D156: Data | G156: 110, 210, 310
A157: TryConfigColorAndAgrField | B157: TipoPrezzo | C157: 2 | D157: TipiPrezzo | G157: PrezzoAcquisto, PrezzoRivendita
A158: TryConfigColorAndAgrField | B158: DescTipoPrezzo | C158: 2 | D158: TipiPrezzo | G158: Prezzo di acquisto, Prezzo di rivendita
A159: TryExtensions | B159: Alpha | C159: 26 | D159: Characters | G159: A, B, C, D, E, F, G, H
...

Sheet LegacyObjects
C2: Legacy objects · QlikView sheet objects
A5: =HYPERLINK("#'Discovery'!A1","« Back to Discovery") | B5: QlikView sheet objects (QlikView documents saved as .qvf): expressions and fields.
A6: App | B6: Object ID | C6: Type | D6: Expressions | E6: Referenced fields | F6: Readable strings
A7: First Qlikview Report | B7: CH01 | C7: GraphProperties | D7: Sum(Quantity) | E7: Order_ID | F7: Tahoma | Tahoma | Sum(Quantity) | CH01 | Sum(Quantity) | 0.0, | Segment 1 | 0.5, | Segment 2 | Arial | Arial | Order_ID | Tahoma | Tahoma | Tahoma | Tahoma | Tahoma | Tahoma | Arial | Arial | Arial | Arial | Tahoma | Arial | Arial | Arial | 0.0, | Segment 1 | 0.5, | Segment 2 | Arial | 1000 | Arial | 0.3 | Order_ID | Sum(Quantity) | 0.0, | Segment 1 | 0.5, | Segment 2
A8: First Qlikview Report | B8: LB01 | C8: ListBoxProperties | E8: Region_Key | F8: Tahoma | Tahoma | Region_Key | LB01 | Region_Key | Tahoma | Tahoma | Tahoma | Tahoma | Tahoma | Tahoma | Arial | Arial | Arial
A9: First Qlikview Report | B9: CS01 | C9: CurrentSelectionProperties | F9: Tahoma | Tahoma | Current Selections | CS01 | Fields | Values | Tahoma | Tahoma | Tahoma | Tahoma | Tahoma | Tahoma | Arial | Arial | Arial
A10: First Qlikview Report | B10: SO01 | C10: SearchObjectProperties | F10: Tahoma | Tahoma | SO01 | Arial | Arial | Arial | Arial | Arial | Arial | Arial | Arial | Arial | Search

Sheet ExpressionFunctions
C2: Expression functions · Qlik functions to translate
A5: =HYPERLINK("#'Discovery'!A1","« Back to Discovery") | B5: Qlik functions used in master measures, variables and chart measures, per app.
A6: App | B6: Function | C6: In master measures | D6: In variables | E6: In chart measures
A7: Executive Dashboard | B7: Sum | C7: 46 | D7: 1 | E7: 0
A8: Executive Dashboard | B8: If | C8: 4 | D8: 1 | E8: 0
A9: Executive Dashboard | B9: count | C9: 5 | D9: 0 | E9: 0
A10: Executive Dashboard | B10: max | C10: 2 | D10: 2 | E10: 0
A11: Executive Dashboard | B11: GetSelectedCount | C11: 2 | D11: 1 | E11: 0
A12: Executive Dashboard | B12: Concat | C12: 0 | D12: 2 | E12: 0
A13: Executive Dashboard | B13: E | C13: 1 | D13: 0 | E13: 0
A14: Executive Dashboard | B14: Minstring | C14: 0 | D14: 1 | E14: 0
A15: Executive Dashboard | B15: Month | C15: 0 | D15: 1 | E15: 0
A16: Helpdesk Management | B16: Count | C16: 12 | D16: 0 | E16: 3
A17: Helpdesk Management | B17: Avg | C17: 3 | D17: 0 | E17: 0
A18: Helpdesk Management | B18: floor | C18: 3 | D18: 0 | E18: 0
... A34: Tutorial creazione nuova app | B34: Distinct | C34: 2 | D34: 0 | E34: 0

Sheet Media
C2: Media · images bundled in the apps
A5: =HYPERLINK("#'Discovery'!A1","« Back to Discovery") | B5: Images bundled in the apps.
A6: App | B6: File | C6: Type | D6: Bytes | E6: Found in
A7: Executive Dashboard | B7: images/image_0.jpg | C7: jpg | D7: 43098 | E7: qvapp_allproperties
A8: Executive Dashboard | B8: images/image_1.jpg | C8: jpg | D8: 8434 | E8: media/79af67e9-ba38-4052-b153-3b72823c6224/storytelling-executivedash_1.jpg
A9: Executive Dashboard | B9: media/executive-dashboard.jpg | C9: jpg | D9: 21779 | E9: media/29ea7d58-6537-413d-9e24-c554c8ad5e03/executive-dashboard.jpg
A10: First Qlikview Report | B10: images/image_0.png | C10: png | D10: 4861 | E10: <file>
A11: Helpdesk Management | B11: images/image_0.jpg | C11: jpg | D11: 57834 | E11: qvapp_allproperties
A12: Helpdesk Management | B12: media/apppages-helpdeskmgmt_3.jpg | C12: jpg | D12: 7931 | E12: media/6de962a1-f681-4277-a7cc-a518ce395e42/apppages-helpdeskmgmt_3.jpg
A13: Helpdesk Management | B13: media/apppages-helpdeskmgmt_2.jpg | C13: jpg | D13: 10017 | E13: media/088c2974-7782-4b3a-976d-634e1c6204f2/apppages-helpdeskmgmt_2.jpg
A14: Helpdesk Management | B14: media/apppages-helpdeskmgmt_1.jpg | C14: jpg | D14: 10582 | E14: media/9a4a9a67-921a-4401-a6ef-adfc729022e0/apppages-helpdeskmgmt_1.jpg
A15: Helpdesk Management | B15: media/storytelling-helpdeskmgmt_1.jpg | C15: jpg | D15: 6289 | E15: media/53e59818-bf3a-46e4-9d64-1a30377263c9/storytelling-helpdeskmgmt_1.jpg
A16: Helpdesk Management | B16: media/helpdesk-management.jpg | C16: jpg | D16: 19692 | E16: media/3f44a200-4710-4c96-8ae5-8f735ddf5958/helpdesk-management.jpg

Sheet StoredObjects
C2: Stored objects · everything inside the .qvf files
A5: =HYPERLINK("#'Discovery'!A1","« Back to Discovery") | B5: Every entry inside every .qvf container.
A6: App | B6: Path | C6: Type | D6: Format | E6: Stored bytes | F6: Modified
A7: Executive Dashboard | B7: qvapp_header | C7: qvapp_header | E7: 193 | F7: 2015-05-21T15:35:59
A8: Executive Dashboard | B8: data/field_4 | C8: qvapp_cfield | E8: 254 | F8: 2015-05-01T18:24:24
A9: Executive Dashboard | B9: data/field_3 | C9: qvapp_cfield | E9: 218 | F9: 2015-05-01T18:24:24
A10: Executive Dashboard | B10: data/field_32 | C10: qvapp_cfield | E10: 3155 | F10: 2015-05-01T18:24:24
A11: Executive Dashboard | B11: data/field_2 | C11: qvapp_cfield | E11: 290 | F11: 2015-05-01T18:24:24
A12: Executive Dashboard | B12: data/field_33 | C12: qvapp_cfield | E12: 40649 | F12: 2015-05-01T18:24:24
A13: Executive Dashboard | B13: data/field_1 | C13: qvapp_cfield | E13: 665 | F13: 2015-05-01T18:24:24
A14: Executive Dashboard | B14: data/field_34 | C14: qvapp_cfield | E14: 220 | F14: 2015-05-01T18:24:24
A15: Executive Dashboard | B15: data/field_6 | C15: qvapp_cfield | E15: 298 | F15: 2015-05-01T18:24:24
A16: Executive Dashboard | B16: data/field_7 | C16: qvapp_cfield | E16: 231 | F16: 2015-05-01T18:24:24
A17: Executive Dashboard | B17: data/field_8 | C17: qvapp_cfield | E17: 518 | F17: 2015-05-01T18:24:24
A18: Executive Dashboard | B18: data/field_9 | C18: qvapp_cfield | E18: 799 | F18: 2015-05-01T18:24:24
... A208: Executive Dashboard | B208: qvapp_approperties | C208: NxAppProperties | E208: 505 | F208: 2015-11-07T21:35:26
A209: Executive Dashboard | B209: media/acf92e2f-3cfc-4e1f-8c9e-442805613b06 | E209: 2285 | F209: 2015-05-20T16:16:55
A210: Executive Dashboard | B210: media/70ca7a28-aa41-4dad-8b2a-39065c2913a2 | E210: 256 | F210: 2015-05-20T19:43:34
A211: Executive Dashboard | B211: media/d530f49c-c735-4d4e-9f99-266d31076d79 | E211: 256 | F211: 2015-05-20T19:43:34
A212: Executive Dashboard | B212: media/24517681-ef6d-4761-952e-389b8d3bd632 | E212: 256 | F212: 2015-05-20T19:44:06
A213: Executive Dashboard | B213: media/79af67e9-ba38-4052-b153-3b72823c6224/storytelling-executivedash_1.jpg | E213: 7966 | F213: 2015-05-20T19:44:35
A214: Executive Dashboard | B214: media/29ea7d58-6537-413d-9e24-c554c8ad5e03/executive-dashboard.jpg | C214: NxQvfBundledItem | E214: 21429 | F214: 2015-05-21T15:29:32
A215: Executive Dashboard | B215: qvapp_variablelist | C215: GenericVariableEntryList | E215: 2285 | F215: 2015-11-07T21:35:26
A216: Executive Dashboard | B216: user_variablelist | C216: GenericVariableEntryList | E216: 81 | F216: 2015-11-07T21:35:26
A217: Executive Dashboard | B217: qvapp_derivedfieldlist | C217: GenericDerivedFieldEntryList | E217: 58 | F217: 2015-11-07T21:35:26
A218: Executive Dashboard | B218: qvapp_deriveddefinitionlist | E218: 58 | F218: 2015-11-07T21:35:26
A219: First Qlikview Report | B219: Document/BM01 | C219: Bookmark | D219: binary | E219: 104 | F219: 2026-09-24T14:02:03
A220: First Qlikview Report | B220: Document/BM02 | C220: Bookmark | D220: binary | E220: 255 | F220: 2026-09-24T14:02:03
A221: First Qlikview Report | B221: CH01 | C221: GraphProperties | D221: binary | E221: 1258 | F221: 2026-09-24T14:02:03
A222: First Qlikview Report | B222: LB01 | C222: ListBoxProperties | D222: binary | E222: 340 | F222: 2026-09-24T14:02:03
A223: First Qlikview Report | B223: CS01 | C223: CurrentSelectionProperties | D223: binary | E223: 389 | F223: 2026-09-24T14:02:03
A224: First Qlikview Report | B224: SO01 | C224: SearchObjectProperties | D224: binary | E224: 270 | F224: 2026-09-24T14:02:03
A225: First Qlikview Report | B225: data/field_0 | C225: qvapp_cfield | E225: 275 | F225: 2026-09-24T14:02:03
A226: First Qlikview Report | B226: data/field_1 | C226: qvapp_cfield | E226: 261 | F226: 2026-09-24T14:02:03
A227: First Qlikview Report | B227: data/field_2 | C227: qvapp_cfield | E227: 191 | F227: 2026-09-24T14:02:03
A228: First Qlikview Report | B228: data/field_3 | C228: qvapp_cfield | E228: 190 | F228: 2026-09-24T14:02:03
A229: First Qlikview Report | B229: data/field_4 | C229: qvapp_cfield | E229: 222 | F229: 2026-09-24T14:02:03
A230: First Qlikview Report | B230: data/field_5 | C230: qvapp_cfield | E230: 185 | F230: 2026-09-24T14:02:03
A231: First Qlikview Report | B231: data/field_6 | C231: qvapp_cfield | E231: 196 | F231: 2026-09-24T14:02:03
A232: First Qlikview Report | B232: data/field_7 | C232: qvapp_cfield | E232: 244 | F232: 2026-09-24T14:02:03
A233: First Qlikview Report | B233: data/field_8 | C233: qvapp_cfield | E233: 215 | F233: 2026-09-24T14:02:03
A234: First Qlikview Report | B234: data/field_9 | C234: qvapp_cfield | E234: 210 | F234: 2026-09-24T14:02:03
A235: First Qlikview Report | B235: data/field_10 | C235: qvapp_cfield | E235: 214 | F235: 2026-09-24T14:02:03
A236: First Qlikview Report | B236: data/field_11 | C236: qvapp_cfield | E236: 229 | F236: 2026-09-24T14:02:03
... A244: First Qlikview Report | B244: data/table_3 | C244: qvapp_ctable | E244: 123 | F244: 2026-09-24T14:02:03
A245: First Qlikview Report | B245: user_variablelist | C245: GenericVariableEntryList | D245: gzjson | E245: 81 | F245: 2026-09-24T14:02:03
A246: First Qlikview Report | B246: qvapp_variablelist | C246: GenericVariableEntryList | D246: gzjson | E246: 455 | F246: 2026-09-24T14:02:03
A247: First Qlikview Report | B247: qvapp_header | C247: qvapp_header | E247: 183 | F247: 2026-09-24T14:02:03
A248: First Qlikview Report | B248: qvapp_allproperties | C248: AllProperties | D248: binary | E248: 142041 | F248: 2026-09-24T14:02:03
A249: First Qlikview Report | B249: qvapp_meta | C249: DataModelMetadata | D249: gzjson | E249: 1215 | F249: 2026-09-24T14:02:03
A250: First Qlikview Report | B250: qvapp_approperties | C250: NxAppProperties | D250: gzjson | E250: 137 | F250: 2026-09-24T14:02:03
A251: First Qlikview Report | B251: qvapp_derivedfieldlist | C251: GenericDerivedFieldEntryList | D251: gzjson | E251: 58 | F251: 2026-09-24T14:02:03
A252: First Qlikview Report | B252: qvapp_deriveddefinitionlist | C252: GenericDerivedDefinitionEntryList | D252: gzjson | E252: 58 | F252: 2026-09-24T14:02:03
A253: First Qlikview Report | B253: qvapp_data | C253: qvapp_cheader | E253: 873 | F253: 2026-09-24T14:02:03
A254: First Qlikview Report | B254: qvapp_qaccess | C254: qvapp_data | E254: 27 | F254: 2026-09-24T14:02:03
A255: Helpdesk Management | B255: qvapp_header | C255: qvapp_header | E255: 193 | F255: 2015-05-21T15:36:34
A256: Helpdesk Management | B256: data/field_2 | C256: qvapp_cfield | E256: 199 | F256: 2015-05-01T18:29:15
A257: Helpdesk Management | B257: data/field_3 | C257: qvapp_cfield | E257: 198 | F257: 2015-05-01T18:29:15
A258: Helpdesk Management | B258: data/field_4 | C258: qvapp_cfield | E258: 241 | F258: 2015-05-01T18:29:15
A259: Helpdesk Management | B259: data/field_5 | C259: qvapp_cfield | E259: 185 | F259: 2015-05-01T18:29:15
A260: Helpdesk Management | B260: data/field_24 | C260: qvapp_cfield | E260: 2606 | F260: 2015-05-01T18:29:15
A261: Helpdesk Management | B261: data/field_1 | C261: qvapp_cfield | E261: 332 | F261: 2015-05-01T18:29:15
A262: Helpdesk Management | B262: data/table_0 | C262: qvapp_ctable | E262: 102986 | F262: 2015-05-01T18:29:15
A263: Helpdesk Management | B263: data/field_0 | C263: qvapp_cfield | E263: 449 | F263: 2015-05-01T18:29:15
A264: Helpdesk Management | B264: data/field_6 | C264: qvapp_cfield | E264: 26406 | F264: 2015-05-01T18:29:15
... A653: Tutorial creazione script | B653: qvapp_qaccess | C653: qvapp_data | E653: 27 | F653: 2016-01-31T22:06:42

Sheet Warnings
C2: Warnings · what discovery could not do
A5: =HYPERLINK("#'Discovery'!A1","« Back to Discovery") | B5: Apps that could not be parsed and anything the parser could not decode. Read this one.
A6: App | B6: # | C6: Message
A7: Sales Analysis | B7: 1 | C7: qlik-parser returned 1 variables without name or id (it reads qData; this app stores qProperties); replaced by qvf-app's 24 named variables

Sheet Information
C2: Information · how to read this workbook
A5: =HYPERLINK("#'Discovery'!A1","« Back to Discovery") | B5: How to read this workbook.
A8: What this workbook is
A9: A discovery report: an inventory of every Qlik app in the input folder, produced by reading the .qvf files offline with qvf-app (built on the open-source qlik-parser). Nothing was reloaded and no data source was contacted. The Discovery sheet shows portfolio figures from Totals; Apps has one row per app; every detail sheet starts with the App column, so filter it to look at one app.
A11: What happens next
A12: Use this workbook to scope the Qlik Sense → Power BI migration: sheets become report pages, visualizations become visuals, master measures and expression variables become DAX measures, master dimensions become model columns and hierarchies, and the load scripts and their data sources become Power Query queries. Start with the Apps sheet (effort score and complexity per app); the weights on Totals are editable.
A14: What each sheet holds
A15: Sheet | B15: Contents
A16: =HYPERLINK("#'Discovery'!A1","Discovery") | B16: The dashboard: portfolio numbers, scan summary and charts. Every figure links to Totals.
A17: =HYPERLINK("#'Apps'!A1","Apps") | B17: One row per app: file, status, every count, effort score and migration complexity (all formulas).
A18: =HYPERLINK("#'Sheets'!A1","Sheets") | B18: One row per sheet in every app: title, description, visualizations on it, master-item reuse.
A19: =HYPERLINK("#'Visualizations'!A1","Visualizations") | B19: Every object on every sheet (including containers and filter panes): type, title, master visualization link, dimensions, measures, grid position.
A20: =HYPERLINK("#'MasterMeasures'!A1","MasterMeasures") | B20: Library measures with the full expression, complexity flags and how often they are used.
A21: =HYPERLINK("#'MasterDimensions'!A1","MasterDimensions") | B21: Library dimensions: fields, single or drill-down, usage.
A22: =HYPERLINK("#'MasterVisualizations'!A1","MasterVisualizations") | B22: Reusable library charts with their dimensions, measures and usage.
A23: =HYPERLINK("#'MasterItemUsage'!A1","MasterItemUsage") | B23: One row per link from a visualization to a master item; feeds the usage counts.
A24: =HYPERLINK("#'Variables'!A1","Variables") | B24: Script and user variables, their definitions and whether they are expressions.
A25: =HYPERLINK("#'Bookmarks'!A1","Bookmarks") | B25: Saved selections with title, description and stored selection text.
A26: =HYPERLINK("#'Stories'!A1","Stories") | B26: Stories with slide and slide-item counts.
A27: =HYPERLINK("#'LoadScript'!A1","LoadScript") | B27: One row per script tab: lines and counts of LOAD, SELECT, STORE, JOIN and other statements.
A28: =HYPERLINK("#'DataSources'!A1","DataSources") | B28: Every connection, SQL query, file, resident and inline load and STORE in every script.
A29: =HYPERLINK("#'DataTables'!A1","DataTables") | B29: Tables stored in each app with source, row and column counts (none when saved without data).
A30: =HYPERLINK("#'Fields'!A1","Fields") | B30: Data-model fields with distinct values, tables, tags and sample values.
A31: =HYPERLINK("#'LegacyObjects'!A1","LegacyObjects") | B31: QlikView sheet objects (QlikView documents saved as .qvf): expressions and fields.
A32: =HYPERLINK("#'ExpressionFunctions'!A1","ExpressionFunctions") | B32: Qlik functions used in master measures, variables and chart measures, per app.
A33: =HYPERLINK("#'Media'!A1","Media") | B33: Images bundled in the apps.
A34: =HYPERLINK("#'StoredObjects'!A1","StoredObjects") | B34: Every entry inside every .qvf container.
A35: =HYPERLINK("#'Warnings'!A1","Warnings") | B35: Apps that could not be parsed and anything the parser could not decode. Read this one.
A36: =HYPERLINK("#'Information'!A1","Information") | B36: How to read this workbook.
A37: =HYPERLINK("#'Totals'!A1","Totals") | B37: The single source of truth for the Discovery sheet: portfolio totals and the effort weights.
A39: What was scanned
A40: Property | B40: Value
A41: Input folder | B41: /home/joginder-singh/workspace/qliksense_to_powerbi_premigration/sample_files
A42: Sub-folders included | B42: No
A43: Output folder | B43: /home/joginder-singh/workspace/qliksense_to_powerbi_premigration/output
A44: Qlik files found | B44: 8
A45: Parsed / failed | B45: 8 / 0
A46: Parsed output | B46: One "<app>_parsed" folder per app in the output folder (report.json, script.qvs, measures.json, data/*.csv, …)
A47: Discovery generated | B47: 2026-10-08 21:41
A49: Limits of this discovery
A50: • Data sources come from pattern matching on the load scripts, not from running them. Paths built from variables show as "Variable path" with the raw $(…) text; $(Include=…) files are not followed.
A51: • "Unused master measures" counts only direct library references (qLibraryId). A measure used only inside another expression, a variable or a set expression is counted as unused.
A52: • QlikView documents saved as .qvf keep sheet objects in a binary format: you get their readable strings, expressions and fields, not typed chart properties.
A53: • Apps saved without data have no field values or rows (Apps → Data stored = No).
A54: • The complexity levels and effort scores are heuristics of this tool, not an industry standard.

Sheet Totals
B2: Totals · the single source of truth
A5: =HYPERLINK("#'Discovery'!A1","« Back to Discovery") | B5: The single source of truth for the Discovery sheet: portfolio totals and the effort weights.
A7: Portfolio
A8: Metric | B8: Value | C8: What it means
A9: Apps discovered | B9: =COUNTA('Apps'!$A$7:$A$100000) | C9: Qlik files found in the input folder
A10: Apps parsed | B10: =COUNTIF('Apps'!$E$7:$E$100000,"Parsed") | C10: Read successfully
A11: Apps failed | B11: =COUNTIF('Apps'!$E$7:$E$100000,"Failed*") | C11: See Warnings
A12: Total size (MB) | B12: =SUM('Apps'!$D$7:$D$100000) | C12: Size of all .qvf/.qvw files
A13: High-complexity apps | B13: =COUNTIF('Apps'!$AE$7:$AE$100000,"High") | C13: Effort score at or above the High threshold
A14: Medium-complexity apps | B14: =COUNTIF('Apps'!$AE$7:$AE$100000,"Medium")
A15: Low-complexity apps | B15: =COUNTIF('Apps'!$AE$7:$AE$100000,"Low")
A16: Portfolio effort score | B16: =SUM('Apps'!$AD$7:$AD$100000) | C16: Sum of the app effort scores
A18: App surface
A19: Metric | B19: Value | C19: What it means
A20: Sheets | B20: =COUNTA('Sheets'!$C$7:$C$100000) | C20: Qlik Sense sheets
A21: Visualizations on sheets | B21: =COUNTA('Visualizations'!$D$7:$D$100000) | C21: Includes objects inside containers and filter panes
A22: Visualization types used | B22: =COUNTIF('Totals'!$D$60:$D$73,">0") | C22: Distinct chart types, see Visualization types below
A23: Visualizations linked to master items | B23: =COUNTIF('Visualizations'!$H$7:$H$100000,"?*") | C23: Sheet objects that reuse a master visualization
A24: Bookmarks | B24: =COUNTA('Bookmarks'!$B$7:$B$100000) | C24: Saved selections
A25: Stories | B25: =COUNTA('Stories'!$B$7:$B$100000) | C25: Data storytelling
A26: Media files | B26: =COUNTA('Media'!$B$7:$B$100000) | C26: Images bundled in the apps
A28: Master library
A29: Metric | B29: Value | C29: What it means
A30: Master measures | B30: =COUNTA('MasterMeasures'!$B$7:$B$100000) | C30: Library measures
A31: Measures with set analysis | B31: =COUNTIF('MasterMeasures'!$G$7:$G$100000,"Yes") | C31: Need CALCULATE / filter logic in DAX
A32: Measures with Aggr() | B32: =COUNTIF('MasterMeasures'!$H$7:$H$100000,"Yes") | C32: Need SUMMARIZE / virtual tables in DAX
A33: High-complexity measures | B33: =COUNTIF('MasterMeasures'!$K$7:$K$100000,"High") | C33: See the Complexity column note on MasterMeasures
A34: Unused master measures | B34: =COUNTIF('MasterMeasures'!$L$7:$L$100000,0) | C34: Not referenced by any visualization (candidates to skip)
A35: Master dimensions | B35: =COUNTA('MasterDimensions'!$B$7:$B$100000) | C35: Library dimensions
A36: Drill-down dimensions | B36: =COUNTIF('MasterDimensions'!$E$7:$E$100000,"Drill-down") | C36: Become hierarchies in Power BI
A37: Master visualizations | B37: =COUNTA('MasterVisualizations'!$B$7:$B$100000) | C37: Reusable library charts
A38: Variables | B38: =COUNTA('Variables'!$B$7:$B$100000) | C38: Script and user variables
A39: Expression variables | B39: =COUNTIF('Variables'!$F$7:$F$100000,"Yes") | C39: Definition starts with "=": become measures
A41: Load script and data
A42: Metric | B42: Value | C42: What it means
A43: Load script tabs | B43: =COUNTA('LoadScript'!$C$7:$C$100000) | C43: Script sections
A44: Load script lines | B44: =SUM('LoadScript'!$D$7:$D$100000) | C44: Including comments
A45: LOAD statements | B45: =SUM('LoadScript'!$E$7:$E$100000) | C45: Become Power Query queries
A46: Data sources referenced | B46: =COUNTA('DataSources'!$D$7:$D$100000) | C46: CONNECT / SQL / FROM / RESIDENT / INLINE / STORE
A47: Distinct external sources | B47: =SUM('DataSources'!$G$7:$G$100000) | C47: Unique connections, files and tables across all apps (no RESIDENT or STORE)
A48: Data tables stored | B48: =COUNTA('DataTables'!$B$7:$B$100000) | C48: 0 for apps saved without data
A49: Data rows stored | B49: =SUM('DataTables'!$D$7:$D$100000) | C49: Rows across all stored tables
A50: Fields | B50: =COUNTA('Fields'!$B$7:$B$100000) | C50: Fields in the data models
A51: Legacy QlikView objects | B51: =COUNTA('LegacyObjects'!$B$7:$B$100000) | C51: Charts, list boxes, … in QlikView documents
A53: Discovery quality
A54: Metric | B54: Value | C54: What it means
A55: Stored objects | B55: =COUNTA('StoredObjects'!$B$7:$B$100000) | C55: Every entry inside the .qvf files
A56: Parser warnings | B56: =COUNTA('Warnings'!$C$7:$C$100000) | C56: Includes apps that failed
A58: Visualization types
A59: Type | B59: On sheets | C59: Master visualizations | D59: Total
A60: HelloWorld | B60: =COUNTIF('Visualizations'!$E$7:$E$100000,A60) | C60: =COUNTIF('MasterVisualizations'!$D$7:$D$100000,A60) | D60: =B60+C60
A61: barchart | B61: =COUNTIF('Visualizations'!$E$7:$E$100000,A61) | C61: =COUNTIF('MasterVisualizations'!$D$7:$D$100000,A61) | D61: =B61+C61
A62: combochart | B62: =COUNTIF('Visualizations'!$E$7:$E$100000,A62) | C62: =COUNTIF('MasterVisualizations'!$D$7:$D$100000,A62) | D62: =B62+C62
A63: filterpane | B63: =COUNTIF('Visualizations'!$E$7:$E$100000,A63) | C63: =COUNTIF('MasterVisualizations'!$D$7:$D$100000,A63) | D63: =B63+C63
A64: gauge | B64: =COUNTIF('Visualizations'!$E$7:$E$100000,A64) | C64: =COUNTIF('MasterVisualizations'!$D$7:$D$100000,A64) | D64: =B64+C64
A65: kpi | B65: =COUNTIF('Visualizations'!$E$7:$E$100000,A65) | C65: =COUNTIF('MasterVisualizations'!$D$7:$D$100000,A65) | D65: =B65+C65
A66: linechart | B66: =COUNTIF('Visualizations'!$E$7:$E$100000,A66) | C66: =COUNTIF('MasterVisualizations'!$D$7:$D$100000,A66) | D66: =B66+C66
A67: listbox | B67: =COUNTIF('Visualizations'!$E$7:$E$100000,A67) | C67: =COUNTIF('MasterVisualizations'!$D$7:$D$100000,A67) | D67: =B67+C67
A68: map | B68: =COUNTIF('Visualizations'!$E$7:$E$100000,A68) | C68: =COUNTIF('MasterVisualizations'!$D$7:$D$100000,A68) | D68: =B68+C68
A69: piechart | B69: =COUNTIF('Visualizations'!$E$7:$E$100000,A69) | C69: =COUNTIF('MasterVisualizations'!$D$7:$D$100000,A69) | D69: =B69+C69
A70: pivot-table | B70: =COUNTIF('Visualizations'!$E$7:$E$100000,A70) | C70: =COUNTIF('MasterVisualizations'!$D$7:$D$100000,A70) | D70: =B70+C70
A71: scatterplot | B71: =COUNTIF('Visualizations'!$E$7:$E$100000,A71) | C71: =COUNTIF('MasterVisualizations'!$D$7:$D$100000,A71) | D71: =B71+C71
... A73: treemap | B73: =COUNTIF('Visualizations'!$E$7:$E$100000,A73) | C73: =COUNTIF('MasterVisualizations'!$D$7:$D$100000,A73) | D73: =B73+C73
A75: Migration effort weights (heuristic)
A76: Driver | B76: Portfolio count | C76: Weight | D76: Points | E76: How to use
A77: Sheets | B77: ='Totals'!$B$20 | C77: 3 | D77: =B77*C77 | E77: Blue cells on yellow are editable (defaults are this tool's assumptions, not an industry standard). Each app's effort score on Apps = Σ its counts × these weights; the rating uses the thresholds below.
A78: Visualizations on sheets | B78: ='Totals'!$B$21 | C78: 1 | D78: =B78*C78
A79: Master measures | B79: ='Totals'!$B$30 | C79: 1 | D79: =B79*C79
A80: Measures with set analysis | B80: ='Totals'!$B$31 | C80: 2 | D80: =B80*C80
A81: Measures with Aggr() | B81: ='Totals'!$B$32 | C81: 3 | D81: =B81*C81
A82: Master dimensions | B82: ='Totals'!$B$35 | C82: 0.5 | D82: =B82*C82
A83: Drill-down dimensions | B83: ='Totals'!$B$36 | C83: 1 | D83: =B83*C83
A84: Master visualizations | B84: ='Totals'!$B$37 | C84: 1 | D84: =B84*C84
A85: Expression variables | B85: ='Totals'!$B$39 | C85: 1 | D85: =B85*C85
A86: Load script tabs | B86: ='Totals'!$B$43 | C86: 2 | D86: =B86*C86
A87: LOAD statements | B87: ='Totals'!$B$45 | C87: 1 | D87: =B87*C87
A88: Distinct external sources | B88: ='Totals'!$B$47 | C88: 3 | D88: =B88*C88
A89: Legacy QlikView objects | B89: ='Totals'!$B$51 | C89: 2 | D89: =B89*C89
A90: Bookmarks | B90: ='Totals'!$B$24 | C90: 0.5 | D90: =B90*C90
A91: Stories | B91: ='Totals'!$B$25 | C91: 2 | D91: =B91*C91
A92: Portfolio points | D92: =SUM(D77:D91)
A93: Medium from app score | C93: 100
A94: High from app score | C94: 400

Sheet ChartVisTypes
A1: Type | B1: Visualizations
A2: ='Totals'!A60 | B2: ='Totals'!D60
A3: ='Totals'!A61 | B3: ='Totals'!D61
A4: ='Totals'!A62 | B4: ='Totals'!D62
A5: ='Totals'!A63 | B5: ='Totals'!D63
A6: ='Totals'!A64 | B6: ='Totals'!D64
A7: ='Totals'!A65 | B7: ='Totals'!D65
A8: ='Totals'!A66 | B8: ='Totals'!D66
A9: ='Totals'!A67 | B9: ='Totals'!D67
A10: ='Totals'!A68 | B10: ='Totals'!D68
A11: ='Totals'!A69 | B11: ='Totals'!D69
A12: ='Totals'!A70 | B12: ='Totals'!D70
A13: ='Totals'!A71 | B13: ='Totals'!D71
... A15: ='Totals'!A73 | B15: ='Totals'!D73

Sheet ChartAppComplexity
A1: Complexity | B1: Apps
A2: Low | B2: ='Totals'!$B$15
A3: Medium | B3: ='Totals'!$B$14
A4: High | B4: ='Totals'!$B$13

Sheet ChartTopApps
A1: App | B1: Effort score
A2: ='Apps'!A7 | B2: ='Apps'!AD7
A3: ='Apps'!A9 | B3: ='Apps'!AD9
A4: ='Apps'!A13 | B4: ='Apps'!AD13
A5: ='Apps'!A10 | B5: ='Apps'!AD10
A6: ='Apps'!A12 | B6: ='Apps'!AD12
A7: ='Apps'!A8 | B7: ='Apps'!AD8
A8: ='Apps'!A11 | B8: ='Apps'!AD11
A9: ='Apps'!A14 | B9: ='Apps'!AD14
